{
  "odata.metadata": "https://datamall2.mytransport.sg/ltaodataservice/$metadata#TaxiAvailability",
  "value": [
    {
      "Longitude": 103.66978,
      "Latitude": 1.26065
    },
    {
      "Longitude": 103.70339,
      "Latitude": 1.26458
    },
    {
      "Longitude": 103.8207602128,
      "Latitude": 1.2647402136
    },
    {
      "Longitude": 103.8205399364,
      "Latitude": 1.265744456
    },
    {
      "Longitude": 103.82032,
      "Latitude": 1.26637
    },
    {
      "Longitude": 103.8582903519,
      "Latitude": 1.2684092495
    },
    {
      "Longitude": 103.828067556,
      "Latitude": 1.2689194146
    },
    {
      "Longitude": 103.8099834323,
      "Latitude": 1.2710160517
    },
    {
      "Longitude": 103.8325076178,
      "Latitude": 1.2724681101
    },
    {
      "Longitude": 103.8442885503,
      "Latitude": 1.2735578238
    },
    {
      "Longitude": 103.7997937202,
      "Latitude": 1.2736399461
    },
    {
      "Longitude": 103.8457208499,
      "Latitude": 1.2737498895
    },
    {
      "Longitude": 103.79911,
      "Latitude": 1.27389
    },
    {
      "Longitude": 103.8083,
      "Latitude": 1.27398
    },
    {
      "Longitude": 103.80146,
      "Latitude": 1.27464
    },
    {
      "Longitude": 103.8400721,
      "Latitude": 1.2747185
    },
    {
      "Longitude": 103.79301,
      "Latitude": 1.27598
    },
    {
      "Longitude": 103.84343,
      "Latitude": 1.27601
    },
    {
      "Longitude": 103.84775,
      "Latitude": 1.27625
    },
    {
      "Longitude": 103.8435,
      "Latitude": 1.2765
    },
    {
      "Longitude": 103.79067,
      "Latitude": 1.27663
    },
    {
      "Longitude": 103.8382519037,
      "Latitude": 1.2767931075
    },
    {
      "Longitude": 103.82933,
      "Latitude": 1.27726
    },
    {
      "Longitude": 103.84048,
      "Latitude": 1.27772
    },
    {
      "Longitude": 103.85822,
      "Latitude": 1.27776
    },
    {
      "Longitude": 103.84087,
      "Latitude": 1.27798
    },
    {
      "Longitude": 103.85194,
      "Latitude": 1.27799
    },
    {
      "Longitude": 103.83551,
      "Latitude": 1.27808
    },
    {
      "Longitude": 103.83751,
      "Latitude": 1.2781
    },
    {
      "Longitude": 103.84693,
      "Latitude": 1.2785951
    },
    {
      "Longitude": 103.85485,
      "Latitude": 1.27884
    },
    {
      "Longitude": 103.7856722251,
      "Latitude": 1.2791676128
    },
    {
      "Longitude": 103.81723,
      "Latitude": 1.27917
    },
    {
      "Longitude": 103.83898,
      "Latitude": 1.27917
    },
    {
      "Longitude": 103.7856249511,
      "Latitude": 1.2792966619
    },
    {
      "Longitude": 103.8527143747,
      "Latitude": 1.2795078332
    },
    {
      "Longitude": 103.84279,
      "Latitude": 1.27994
    },
    {
      "Longitude": 103.8270737976,
      "Latitude": 1.2802053688
    },
    {
      "Longitude": 103.85315,
      "Latitude": 1.28042
    },
    {
      "Longitude": 103.85815,
      "Latitude": 1.28053
    },
    {
      "Longitude": 103.8512512296,
      "Latitude": 1.2810607797
    },
    {
      "Longitude": 103.84214,
      "Latitude": 1.2811
    },
    {
      "Longitude": 103.8500740752,
      "Latitude": 1.2813487099
    },
    {
      "Longitude": 103.8515,
      "Latitude": 1.28153
    },
    {
      "Longitude": 103.8503671065,
      "Latitude": 1.2817646835
    },
    {
      "Longitude": 103.85994,
      "Latitude": 1.28204
    },
    {
      "Longitude": 103.8503600657,
      "Latitude": 1.2820750715
    },
    {
      "Longitude": 103.8340753689,
      "Latitude": 1.2823777501
    },
    {
      "Longitude": 103.85103,
      "Latitude": 1.28245
    },
    {
      "Longitude": 103.8503372669,
      "Latitude": 1.2826626634
    },
    {
      "Longitude": 103.8361239061,
      "Latitude": 1.2828761807
    },
    {
      "Longitude": 103.8421622291,
      "Latitude": 1.282942884
    },
    {
      "Longitude": 103.81612,
      "Latitude": 1.28327
    },
    {
      "Longitude": 103.84247,
      "Latitude": 1.2833
    },
    {
      "Longitude": 103.8508613035,
      "Latitude": 1.2837386298
    },
    {
      "Longitude": 103.84921,
      "Latitude": 1.28423
    },
    {
      "Longitude": 103.79939,
      "Latitude": 1.28497
    },
    {
      "Longitude": 103.84295,
      "Latitude": 1.28531
    },
    {
      "Longitude": 103.8450107351,
      "Latitude": 1.2860025154
    },
    {
      "Longitude": 103.8274714351,
      "Latitude": 1.2866832896
    },
    {
      "Longitude": 103.81033,
      "Latitude": 1.28678
    },
    {
      "Longitude": 103.85893,
      "Latitude": 1.28967
    },
    {
      "Longitude": 103.77032,
      "Latitude": 1.29025
    },
    {
      "Longitude": 103.85482,
      "Latitude": 1.29117
    },
    {
      "Longitude": 103.8547870517,
      "Latitude": 1.2912586507
    },
    {
      "Longitude": 103.85108,
      "Latitude": 1.29164
    },
    {
      "Longitude": 103.83998,
      "Latitude": 1.29167
    },
    {
      "Longitude": 103.8504,
      "Latitude": 1.2922
    },
    {
      "Longitude": 103.8505,
      "Latitude": 1.29221
    },
    {
      "Longitude": 103.79871,
      "Latitude": 1.29328
    },
    {
      "Longitude": 103.80547,
      "Latitude": 1.29349
    },
    {
      "Longitude": 103.8270878792,
      "Latitude": 1.2938111288
    },
    {
      "Longitude": 103.78449,
      "Latitude": 1.29397
    },
    {
      "Longitude": 103.8565609977,
      "Latitude": 1.29406822
    },
    {
      "Longitude": 103.78412,
      "Latitude": 1.29445
    },
    {
      "Longitude": 103.7844836712,
      "Latitude": 1.2948770348
    },
    {
      "Longitude": 103.79204,
      "Latitude": 1.29531
    },
    {
      "Longitude": 103.621796295,
      "Latitude": 1.2953372514
    },
    {
      "Longitude": 103.7842489779,
      "Latitude": 1.2954481994
    },
    {
      "Longitude": 103.7857127935,
      "Latitude": 1.296403492
    },
    {
      "Longitude": 103.7867,
      "Latitude": 1.29646
    },
    {
      "Longitude": 103.7901085988,
      "Latitude": 1.2974499559
    },
    {
      "Longitude": 103.88465,
      "Latitude": 1.29801
    },
    {
      "Longitude": 103.78532,
      "Latitude": 1.29854
    },
    {
      "Longitude": 103.7668401003,
      "Latitude": 1.2992371892
    },
    {
      "Longitude": 103.85139,
      "Latitude": 1.3001
    },
    {
      "Longitude": 103.85704,
      "Latitude": 1.30013
    },
    {
      "Longitude": 103.7624486536,
      "Latitude": 1.300944311
    },
    {
      "Longitude": 103.78984,
      "Latitude": 1.30098
    },
    {
      "Longitude": 103.6795134097,
      "Latitude": 1.3016110032
    },
    {
      "Longitude": 103.91194,
      "Latitude": 1.30195
    },
    {
      "Longitude": 103.6299143359,
      "Latitude": 1.3024767978
    },
    {
      "Longitude": 103.7872,
      "Latitude": 1.30326
    },
    {
      "Longitude": 103.83446,
      "Latitude": 1.30355
    },
    {
      "Longitude": 103.679205291,
      "Latitude": 1.3040354285
    },
    {
      "Longitude": 103.8497082889,
      "Latitude": 1.3043541935
    },
    {
      "Longitude": 103.82568,
      "Latitude": 1.30468
    },
    {
      "Longitude": 103.7498255074,
      "Latitude": 1.3047225665
    },
    {
      "Longitude": 103.76073,
      "Latitude": 1.30481
    },
    {
      "Longitude": 103.79212,
      "Latitude": 1.30514
    },
    {
      "Longitude": 103.78961,
      "Latitude": 1.30518
    },
    {
      "Longitude": 103.8600602746,
      "Latitude": 1.3056302587
    },
    {
      "Longitude": 103.7580712885,
      "Latitude": 1.3057184134
    },
    {
      "Longitude": 103.7898,
      "Latitude": 1.30577
    },
    {
      "Longitude": 103.9046476409,
      "Latitude": 1.3057995292
    },
    {
      "Longitude": 103.79218,
      "Latitude": 1.30604
    },
    {
      "Longitude": 103.7354052812,
      "Latitude": 1.3063743783
    },
    {
      "Longitude": 103.75908,
      "Latitude": 1.30669
    },
    {
      "Longitude": 103.7116298452,
      "Latitude": 1.3068037554
    },
    {
      "Longitude": 103.87426,
      "Latitude": 1.30692
    },
    {
      "Longitude": 103.7910768762,
      "Latitude": 1.3075532377
    },
    {
      "Longitude": 103.79104,
      "Latitude": 1.30764
    },
    {
      "Longitude": 103.87693,
      "Latitude": 1.30774
    },
    {
      "Longitude": 103.8300785422,
      "Latitude": 1.3077687641
    },
    {
      "Longitude": 103.78773,
      "Latitude": 1.30778
    },
    {
      "Longitude": 103.6652863026,
      "Latitude": 1.307814685
    },
    {
      "Longitude": 103.7905628979,
      "Latitude": 1.308041943
    },
    {
      "Longitude": 103.77217,
      "Latitude": 1.30883
    },
    {
      "Longitude": 103.84602,
      "Latitude": 1.30956
    },
    {
      "Longitude": 103.7895,
      "Latitude": 1.30966
    },
    {
      "Longitude": 103.7682610005,
      "Latitude": 1.3099374347
    },
    {
      "Longitude": 103.84745,
      "Latitude": 1.31001
    },
    {
      "Longitude": 103.710029237,
      "Latitude": 1.310090951
    },
    {
      "Longitude": 103.67869,
      "Latitude": 1.31017
    },
    {
      "Longitude": 103.7177027017,
      "Latitude": 1.3102391043
    },
    {
      "Longitude": 103.75604,
      "Latitude": 1.31026
    },
    {
      "Longitude": 103.75922,
      "Latitude": 1.31144
    },
    {
      "Longitude": 103.78754,
      "Latitude": 1.31157
    },
    {
      "Longitude": 103.85854,
      "Latitude": 1.3119
    },
    {
      "Longitude": 103.8639236614,
      "Latitude": 1.3119934801
    },
    {
      "Longitude": 103.84471,
      "Latitude": 1.31255
    },
    {
      "Longitude": 103.76657,
      "Latitude": 1.31263
    },
    {
      "Longitude": 103.70377,
      "Latitude": 1.31373
    },
    {
      "Longitude": 103.85552,
      "Latitude": 1.31376
    },
    {
      "Longitude": 103.73493,
      "Latitude": 1.31412
    },
    {
      "Longitude": 103.6884508654,
      "Latitude": 1.3147839206
    },
    {
      "Longitude": 103.6787074059,
      "Latitude": 1.3149800055
    },
    {
      "Longitude": 103.65532,
      "Latitude": 1.31537
    },
    {
      "Longitude": 103.6551,
      "Latitude": 1.3156
    },
    {
      "Longitude": 103.65657,
      "Latitude": 1.31563
    },
    {
      "Longitude": 103.776965104,
      "Latitude": 1.316119979
    },
    {
      "Longitude": 103.87591,
      "Latitude": 1.31647
    },
    {
      "Longitude": 103.9051,
      "Latitude": 1.3173
    },
    {
      "Longitude": 103.86304,
      "Latitude": 1.31747
    },
    {
      "Longitude": 103.89219,
      "Latitude": 1.31748
    },
    {
      "Longitude": 103.72315,
      "Latitude": 1.31791
    },
    {
      "Longitude": 103.7482,
      "Latitude": 1.31795
    },
    {
      "Longitude": 103.7100637704,
      "Latitude": 1.3182997035
    },
    {
      "Longitude": 103.85095,
      "Latitude": 1.31839
    },
    {
      "Longitude": 103.9528150856,
      "Latitude": 1.3184719898
    },
    {
      "Longitude": 103.85517,
      "Latitude": 1.31849
    },
    {
      "Longitude": 103.7568897754,
      "Latitude": 1.318515229
    },
    {
      "Longitude": 103.8604,
      "Latitude": 1.31862
    },
    {
      "Longitude": 103.90208,
      "Latitude": 1.31864
    },
    {
      "Longitude": 103.8641613722,
      "Latitude": 1.3190240434
    },
    {
      "Longitude": 103.86153,
      "Latitude": 1.31915
    },
    {
      "Longitude": 103.88731,
      "Latitude": 1.31917
    },
    {
      "Longitude": 103.7102967873,
      "Latitude": 1.3193826937
    },
    {
      "Longitude": 103.7103423849,
      "Latitude": 1.3199518416
    },
    {
      "Longitude": 103.74854,
      "Latitude": 1.32014
    },
    {
      "Longitude": 103.71017,
      "Latitude": 1.32016
    },
    {
      "Longitude": 103.7103205919,
      "Latitude": 1.3203131733
    },
    {
      "Longitude": 103.76233,
      "Latitude": 1.32038
    },
    {
      "Longitude": 103.84468,
      "Latitude": 1.32053
    },
    {
      "Longitude": 103.71015,
      "Latitude": 1.32055
    },
    {
      "Longitude": 103.7479,
      "Latitude": 1.32062
    },
    {
      "Longitude": 103.71016,
      "Latitude": 1.32067
    },
    {
      "Longitude": 103.91272,
      "Latitude": 1.32078
    },
    {
      "Longitude": 103.8905110583,
      "Latitude": 1.3213026455
    },
    {
      "Longitude": 103.84472,
      "Latitude": 1.32167
    },
    {
      "Longitude": 103.91375,
      "Latitude": 1.32196
    },
    {
      "Longitude": 103.7131235003,
      "Latitude": 1.3223299934
    },
    {
      "Longitude": 103.7456556782,
      "Latitude": 1.3226212707
    },
    {
      "Longitude": 103.68166,
      "Latitude": 1.32284
    },
    {
      "Longitude": 103.85596,
      "Latitude": 1.32284
    },
    {
      "Longitude": 103.6780076846,
      "Latitude": 1.322876683
    },
    {
      "Longitude": 103.8688689843,
      "Latitude": 1.323519236
    },
    {
      "Longitude": 103.92944,
      "Latitude": 1.32388
    },
    {
      "Longitude": 103.7194390967,
      "Latitude": 1.3240119604
    },
    {
      "Longitude": 103.941593729,
      "Latitude": 1.325155952
    },
    {
      "Longitude": 103.87454,
      "Latitude": 1.32603
    },
    {
      "Longitude": 103.7255458161,
      "Latitude": 1.3261983817
    },
    {
      "Longitude": 103.764108941,
      "Latitude": 1.32626743
    },
    {
      "Longitude": 103.7470608205,
      "Latitude": 1.326391449
    },
    {
      "Longitude": 103.6792498827,
      "Latitude": 1.326918697
    },
    {
      "Longitude": 103.67928,
      "Latitude": 1.32732
    },
    {
      "Longitude": 103.73782,
      "Latitude": 1.32741
    },
    {
      "Longitude": 103.70852,
      "Latitude": 1.32746
    },
    {
      "Longitude": 103.67886,
      "Latitude": 1.32759
    },
    {
      "Longitude": 103.93481,
      "Latitude": 1.32788
    },
    {
      "Longitude": 103.94401,
      "Latitude": 1.32799
    },
    {
      "Longitude": 103.8681,
      "Latitude": 1.32831
    },
    {
      "Longitude": 103.87075,
      "Latitude": 1.32837
    },
    {
      "Longitude": 103.74935,
      "Latitude": 1.32926
    },
    {
      "Longitude": 103.92681,
      "Latitude": 1.32963
    },
    {
      "Longitude": 103.93706,
      "Latitude": 1.3297
    },
    {
      "Longitude": 103.9274698868,
      "Latitude": 1.3298442005
    },
    {
      "Longitude": 103.90449,
      "Latitude": 1.32994
    },
    {
      "Longitude": 103.6773844063,
      "Latitude": 1.330276255
    },
    {
      "Longitude": 103.67939,
      "Latitude": 1.33028
    },
    {
      "Longitude": 103.89604,
      "Latitude": 1.33035
    },
    {
      "Longitude": 103.6775523797,
      "Latitude": 1.3304106645
    },
    {
      "Longitude": 103.91002,
      "Latitude": 1.33046
    },
    {
      "Longitude": 103.74684,
      "Latitude": 1.33172
    },
    {
      "Longitude": 103.93248,
      "Latitude": 1.3327
    },
    {
      "Longitude": 103.96496,
      "Latitude": 1.33277
    },
    {
      "Longitude": 103.96504,
      "Latitude": 1.3332
    },
    {
      "Longitude": 103.90053,
      "Latitude": 1.3335
    },
    {
      "Longitude": 103.74772,
      "Latitude": 1.33374
    },
    {
      "Longitude": 103.9051183686,
      "Latitude": 1.3341406087
    },
    {
      "Longitude": 103.6965,
      "Latitude": 1.3343
    },
    {
      "Longitude": 103.6964529008,
      "Latitude": 1.3343219439
    },
    {
      "Longitude": 103.90606,
      "Latitude": 1.33437
    },
    {
      "Longitude": 103.8782687858,
      "Latitude": 1.3344613809
    },
    {
      "Longitude": 103.65143,
      "Latitude": 1.33457
    },
    {
      "Longitude": 103.7026,
      "Latitude": 1.33487
    },
    {
      "Longitude": 103.69581,
      "Latitude": 1.33493
    },
    {
      "Longitude": 103.7425,
      "Latitude": 1.33506
    },
    {
      "Longitude": 103.70551,
      "Latitude": 1.33535
    },
    {
      "Longitude": 103.69871,
      "Latitude": 1.33564
    },
    {
      "Longitude": 103.9612167701,
      "Latitude": 1.3358410028
    },
    {
      "Longitude": 103.9589110762,
      "Latitude": 1.336348808
    },
    {
      "Longitude": 103.97036,
      "Latitude": 1.33645
    },
    {
      "Longitude": 103.8929538801,
      "Latitude": 1.336743991
    },
    {
      "Longitude": 103.9587135985,
      "Latitude": 1.3370744833
    },
    {
      "Longitude": 103.95968,
      "Latitude": 1.33717
    },
    {
      "Longitude": 103.71717,
      "Latitude": 1.33724
    },
    {
      "Longitude": 103.6485794932,
      "Latitude": 1.3372487794
    },
    {
      "Longitude": 103.9697649702,
      "Latitude": 1.3374193885
    },
    {
      "Longitude": 103.7009456009,
      "Latitude": 1.3376898826
    },
    {
      "Longitude": 103.85231,
      "Latitude": 1.33773
    },
    {
      "Longitude": 103.74076,
      "Latitude": 1.33786
    },
    {
      "Longitude": 103.7069490552,
      "Latitude": 1.3386873922
    },
    {
      "Longitude": 103.7069604546,
      "Latitude": 1.338721581
    },
    {
      "Longitude": 103.68948,
      "Latitude": 1.33895
    },
    {
      "Longitude": 103.8886398822,
      "Latitude": 1.339010175
    },
    {
      "Longitude": 103.68816,
      "Latitude": 1.33954
    },
    {
      "Longitude": 103.71138,
      "Latitude": 1.34122
    },
    {
      "Longitude": 103.711695224,
      "Latitude": 1.341251218
    },
    {
      "Longitude": 103.7425815314,
      "Latitude": 1.3413058531
    },
    {
      "Longitude": 103.83805,
      "Latitude": 1.3418
    },
    {
      "Longitude": 103.689324595,
      "Latitude": 1.3418793533
    },
    {
      "Longitude": 103.7213615701,
      "Latitude": 1.3422845909
    },
    {
      "Longitude": 103.69268,
      "Latitude": 1.34271
    },
    {
      "Longitude": 103.85833,
      "Latitude": 1.34316
    },
    {
      "Longitude": 103.76985,
      "Latitude": 1.34321
    },
    {
      "Longitude": 103.6873203143,
      "Latitude": 1.3436849898
    },
    {
      "Longitude": 103.73112,
      "Latitude": 1.34371
    },
    {
      "Longitude": 103.89898,
      "Latitude": 1.34388
    },
    {
      "Longitude": 103.93838,
      "Latitude": 1.34401
    },
    {
      "Longitude": 103.91859,
      "Latitude": 1.34461
    },
    {
      "Longitude": 103.94085,
      "Latitude": 1.34463
    },
    {
      "Longitude": 103.70817,
      "Latitude": 1.34478
    },
    {
      "Longitude": 103.74855,
      "Latitude": 1.34519
    },
    {
      "Longitude": 103.95775,
      "Latitude": 1.34537
    },
    {
      "Longitude": 103.70938,
      "Latitude": 1.34566
    },
    {
      "Longitude": 103.747237511,
      "Latitude": 1.3456719593
    },
    {
      "Longitude": 103.7512829527,
      "Latitude": 1.3457758662
    },
    {
      "Longitude": 103.71203,
      "Latitude": 1.34583
    },
    {
      "Longitude": 103.6967714131,
      "Latitude": 1.3458720639
    },
    {
      "Longitude": 103.69691,
      "Latitude": 1.3467
    },
    {
      "Longitude": 103.72593,
      "Latitude": 1.3467
    },
    {
      "Longitude": 103.9852423221,
      "Latitude": 1.3468578388
    },
    {
      "Longitude": 103.7351836637,
      "Latitude": 1.3470716859
    },
    {
      "Longitude": 103.69173,
      "Latitude": 1.34742
    },
    {
      "Longitude": 103.6969802901,
      "Latitude": 1.3479408164
    },
    {
      "Longitude": 103.71239,
      "Latitude": 1.34797
    },
    {
      "Longitude": 103.93835,
      "Latitude": 1.34797
    },
    {
      "Longitude": 103.96996,
      "Latitude": 1.34825
    },
    {
      "Longitude": 103.84709,
      "Latitude": 1.34862
    },
    {
      "Longitude": 103.75766,
      "Latitude": 1.34865
    },
    {
      "Longitude": 103.70518,
      "Latitude": 1.34869
    },
    {
      "Longitude": 103.76076,
      "Latitude": 1.34869
    },
    {
      "Longitude": 103.94778,
      "Latitude": 1.34891
    },
    {
      "Longitude": 103.9649222419,
      "Latitude": 1.3492383108
    },
    {
      "Longitude": 103.72509,
      "Latitude": 1.34931
    },
    {
      "Longitude": 103.9509415627,
      "Latitude": 1.3495041111
    },
    {
      "Longitude": 103.70587,
      "Latitude": 1.34951
    },
    {
      "Longitude": 103.72971,
      "Latitude": 1.34958
    },
    {
      "Longitude": 103.7256876,
      "Latitude": 1.3501146
    },
    {
      "Longitude": 103.72592,
      "Latitude": 1.3502
    },
    {
      "Longitude": 103.9519742131,
      "Latitude": 1.3502073252
    },
    {
      "Longitude": 103.7033716589,
      "Latitude": 1.3502180511
    },
    {
      "Longitude": 103.9594109729,
      "Latitude": 1.3505813894
    },
    {
      "Longitude": 103.93347,
      "Latitude": 1.35065
    },
    {
      "Longitude": 103.70869,
      "Latitude": 1.35098
    },
    {
      "Longitude": 103.95574,
      "Latitude": 1.35109
    },
    {
      "Longitude": 103.83768,
      "Latitude": 1.35169
    },
    {
      "Longitude": 103.98656,
      "Latitude": 1.35182
    },
    {
      "Longitude": 103.98464,
      "Latitude": 1.35195
    },
    {
      "Longitude": 103.7117,
      "Latitude": 1.35217
    },
    {
      "Longitude": 103.96408,
      "Latitude": 1.35228
    },
    {
      "Longitude": 103.88917,
      "Latitude": 1.35267
    },
    {
      "Longitude": 103.86715,
      "Latitude": 1.35338
    },
    {
      "Longitude": 103.69755,
      "Latitude": 1.35534
    },
    {
      "Longitude": 103.74314,
      "Latitude": 1.3557
    },
    {
      "Longitude": 103.9417845011,
      "Latitude": 1.3562902193
    },
    {
      "Longitude": 103.7474701926,
      "Latitude": 1.3564102145
    },
    {
      "Longitude": 103.95022,
      "Latitude": 1.357
    },
    {
      "Longitude": 103.75046,
      "Latitude": 1.35708
    },
    {
      "Longitude": 103.98952,
      "Latitude": 1.35733
    },
    {
      "Longitude": 103.98978,
      "Latitude": 1.35759
    },
    {
      "Longitude": 103.98904,
      "Latitude": 1.35787
    },
    {
      "Longitude": 103.73904,
      "Latitude": 1.35829
    },
    {
      "Longitude": 103.9619272202,
      "Latitude": 1.3585007449
    },
    {
      "Longitude": 103.98885,
      "Latitude": 1.35855
    },
    {
      "Longitude": 103.75157,
      "Latitude": 1.35871
    },
    {
      "Longitude": 103.9353,
      "Latitude": 1.35896
    },
    {
      "Longitude": 103.9493496716,
      "Latitude": 1.3592260784
    },
    {
      "Longitude": 103.93465,
      "Latitude": 1.36019
    },
    {
      "Longitude": 103.9886,
      "Latitude": 1.36057
    },
    {
      "Longitude": 103.98884,
      "Latitude": 1.36115
    },
    {
      "Longitude": 103.70288,
      "Latitude": 1.36126
    },
    {
      "Longitude": 103.9714805782,
      "Latitude": 1.3613802908
    },
    {
      "Longitude": 103.89305,
      "Latitude": 1.36158
    },
    {
      "Longitude": 103.7036308274,
      "Latitude": 1.3622266239
    },
    {
      "Longitude": 103.85686,
      "Latitude": 1.36246
    },
    {
      "Longitude": 103.9054841548,
      "Latitude": 1.3637778428
    },
    {
      "Longitude": 103.87835,
      "Latitude": 1.36391
    },
    {
      "Longitude": 103.96821,
      "Latitude": 1.3642
    },
    {
      "Longitude": 103.8433819637,
      "Latitude": 1.3653967672
    },
    {
      "Longitude": 103.82823,
      "Latitude": 1.36696
    },
    {
      "Longitude": 103.89743,
      "Latitude": 1.36739
    },
    {
      "Longitude": 103.85805,
      "Latitude": 1.36901
    },
    {
      "Longitude": 103.94917,
      "Latitude": 1.37073
    },
    {
      "Longitude": 103.9707,
      "Latitude": 1.37114
    },
    {
      "Longitude": 103.83663,
      "Latitude": 1.37156
    },
    {
      "Longitude": 103.83776735,
      "Latitude": 1.3717588833
    },
    {
      "Longitude": 103.8856770471,
      "Latitude": 1.3728059302
    },
    {
      "Longitude": 103.7410691008,
      "Latitude": 1.3728404537
    },
    {
      "Longitude": 103.77085,
      "Latitude": 1.37401
    },
    {
      "Longitude": 103.9746680483,
      "Latitude": 1.3741818433
    },
    {
      "Longitude": 103.77503,
      "Latitude": 1.37425
    },
    {
      "Longitude": 103.9610427618,
      "Latitude": 1.3744000452
    },
    {
      "Longitude": 103.8462130353,
      "Latitude": 1.374444289
    },
    {
      "Longitude": 103.973,
      "Latitude": 1.37461
    },
    {
      "Longitude": 103.94349,
      "Latitude": 1.37488
    },
    {
      "Longitude": 103.9518712834,
      "Latitude": 1.3749923076
    },
    {
      "Longitude": 103.96454,
      "Latitude": 1.37503
    },
    {
      "Longitude": 103.7407,
      "Latitude": 1.37518
    },
    {
      "Longitude": 103.9763970673,
      "Latitude": 1.3754089358
    },
    {
      "Longitude": 103.97687,
      "Latitude": 1.37588
    },
    {
      "Longitude": 103.8538,
      "Latitude": 1.376
    },
    {
      "Longitude": 103.83921,
      "Latitude": 1.37712
    },
    {
      "Longitude": 103.86691,
      "Latitude": 1.37725
    },
    {
      "Longitude": 103.88914,
      "Latitude": 1.37741
    },
    {
      "Longitude": 103.84484,
      "Latitude": 1.37751
    },
    {
      "Longitude": 103.88335,
      "Latitude": 1.37776
    },
    {
      "Longitude": 103.73767,
      "Latitude": 1.37788
    },
    {
      "Longitude": 103.7365351617,
      "Latitude": 1.3781835504
    },
    {
      "Longitude": 103.74082,
      "Latitude": 1.37822
    },
    {
      "Longitude": 103.87175,
      "Latitude": 1.37839
    },
    {
      "Longitude": 103.76152,
      "Latitude": 1.37895
    },
    {
      "Longitude": 103.9422964677,
      "Latitude": 1.3790905449
    },
    {
      "Longitude": 103.88499,
      "Latitude": 1.3793
    },
    {
      "Longitude": 103.83781,
      "Latitude": 1.3797
    },
    {
      "Longitude": 103.76175,
      "Latitude": 1.37979
    },
    {
      "Longitude": 103.90349,
      "Latitude": 1.38012
    },
    {
      "Longitude": 103.73788,
      "Latitude": 1.38024
    },
    {
      "Longitude": 103.73888,
      "Latitude": 1.38109
    },
    {
      "Longitude": 103.87986,
      "Latitude": 1.38123
    },
    {
      "Longitude": 103.87689,
      "Latitude": 1.38136
    },
    {
      "Longitude": 103.9387066662,
      "Latitude": 1.3814750072
    },
    {
      "Longitude": 103.7432483956,
      "Latitude": 1.3815366801
    },
    {
      "Longitude": 103.83586,
      "Latitude": 1.382
    },
    {
      "Longitude": 103.76077,
      "Latitude": 1.38378
    },
    {
      "Longitude": 103.82849,
      "Latitude": 1.38491
    },
    {
      "Longitude": 103.8838098943,
      "Latitude": 1.3852900078
    },
    {
      "Longitude": 103.90125,
      "Latitude": 1.3853
    },
    {
      "Longitude": 103.84827,
      "Latitude": 1.38543
    },
    {
      "Longitude": 103.74645,
      "Latitude": 1.38555
    },
    {
      "Longitude": 103.90058,
      "Latitude": 1.38602
    },
    {
      "Longitude": 103.89121,
      "Latitude": 1.38638
    },
    {
      "Longitude": 103.82091,
      "Latitude": 1.38646
    },
    {
      "Longitude": 103.9135217294,
      "Latitude": 1.386924671
    },
    {
      "Longitude": 103.8425434381,
      "Latitude": 1.3872957129
    },
    {
      "Longitude": 103.98758,
      "Latitude": 1.38745
    },
    {
      "Longitude": 103.89755,
      "Latitude": 1.38789
    },
    {
      "Longitude": 103.90605,
      "Latitude": 1.38806
    },
    {
      "Longitude": 103.84874,
      "Latitude": 1.3882
    },
    {
      "Longitude": 103.84195,
      "Latitude": 1.3884
    },
    {
      "Longitude": 103.86731,
      "Latitude": 1.38851
    },
    {
      "Longitude": 103.74414,
      "Latitude": 1.38867
    },
    {
      "Longitude": 103.9116723463,
      "Latitude": 1.3897351361
    },
    {
      "Longitude": 103.99237,
      "Latitude": 1.39037
    },
    {
      "Longitude": 103.83978948,
      "Latitude": 1.3903934246
    },
    {
      "Longitude": 103.9122087881,
      "Latitude": 1.3903981171
    },
    {
      "Longitude": 103.7401226163,
      "Latitude": 1.3904302941
    },
    {
      "Longitude": 103.8974563032,
      "Latitude": 1.3905006814
    },
    {
      "Longitude": 103.991545178,
      "Latitude": 1.3906495001
    },
    {
      "Longitude": 103.9118,
      "Latitude": 1.39076
    },
    {
      "Longitude": 103.8723877072,
      "Latitude": 1.391331586
    },
    {
      "Longitude": 103.69099,
      "Latitude": 1.39154
    },
    {
      "Longitude": 103.8486250117,
      "Latitude": 1.3917964768
    },
    {
      "Longitude": 103.7404498458,
      "Latitude": 1.3921474074
    },
    {
      "Longitude": 103.85156,
      "Latitude": 1.3925
    },
    {
      "Longitude": 103.75071,
      "Latitude": 1.39265
    },
    {
      "Longitude": 103.9012204483,
      "Latitude": 1.393272932
    },
    {
      "Longitude": 103.8756,
      "Latitude": 1.39502
    },
    {
      "Longitude": 103.83244,
      "Latitude": 1.39512
    },
    {
      "Longitude": 103.74551,
      "Latitude": 1.39688
    },
    {
      "Longitude": 103.90852,
      "Latitude": 1.39705
    },
    {
      "Longitude": 103.74748,
      "Latitude": 1.39707
    },
    {
      "Longitude": 103.82895,
      "Latitude": 1.39777
    },
    {
      "Longitude": 103.90707,
      "Latitude": 1.39879
    },
    {
      "Longitude": 103.9059099555,
      "Latitude": 1.399929873
    },
    {
      "Longitude": 103.90573,
      "Latitude": 1.40166
    },
    {
      "Longitude": 103.91191,
      "Latitude": 1.40248
    },
    {
      "Longitude": 103.9118,
      "Latitude": 1.40259
    },
    {
      "Longitude": 103.7492169812,
      "Latitude": 1.4029172953
    },
    {
      "Longitude": 103.75625,
      "Latitude": 1.40603
    },
    {
      "Longitude": 103.8590222597,
      "Latitude": 1.4079623534
    },
    {
      "Longitude": 103.8314172998,
      "Latitude": 1.4101969634
    },
    {
      "Longitude": 103.90081,
      "Latitude": 1.41284
    },
    {
      "Longitude": 103.75565,
      "Latitude": 1.4136
    },
    {
      "Longitude": 103.8343137503,
      "Latitude": 1.4139039913
    },
    {
      "Longitude": 103.8415399566,
      "Latitude": 1.4160199441
    },
    {
      "Longitude": 103.7437777966,
      "Latitude": 1.4167093963
    },
    {
      "Longitude": 103.8333719596,
      "Latitude": 1.4173224289
    },
    {
      "Longitude": 103.84028,
      "Latitude": 1.41775
    },
    {
      "Longitude": 103.91017,
      "Latitude": 1.41801
    },
    {
      "Longitude": 103.8325864077,
      "Latitude": 1.4229164687
    },
    {
      "Longitude": 103.83678,
      "Latitude": 1.42331
    },
    {
      "Longitude": 103.83874,
      "Latitude": 1.42353
    },
    {
      "Longitude": 103.84008,
      "Latitude": 1.4238
    },
    {
      "Longitude": 103.84427,
      "Latitude": 1.42503
    },
    {
      "Longitude": 103.7622722983,
      "Latitude": 1.4257969414
    },
    {
      "Longitude": 103.8277272508,
      "Latitude": 1.42587202
    },
    {
      "Longitude": 103.843024224,
      "Latitude": 1.4261854061
    },
    {
      "Longitude": 103.83055,
      "Latitude": 1.42669
    },
    {
      "Longitude": 103.84742,
      "Latitude": 1.42707
    },
    {
      "Longitude": 103.79446,
      "Latitude": 1.42717
    },
    {
      "Longitude": 103.8701758906,
      "Latitude": 1.4273383984
    },
    {
      "Longitude": 103.8352438062,
      "Latitude": 1.4288325951
    },
    {
      "Longitude": 103.83518,
      "Latitude": 1.42887
    },
    {
      "Longitude": 103.84314,
      "Latitude": 1.43107
    },
    {
      "Longitude": 103.78047,
      "Latitude": 1.43131
    },
    {
      "Longitude": 103.79391,
      "Latitude": 1.43167
    },
    {
      "Longitude": 103.84224,
      "Latitude": 1.43176
    },
    {
      "Longitude": 103.79683,
      "Latitude": 1.43181
    },
    {
      "Longitude": 103.7864644825,
      "Latitude": 1.4319969506
    },
    {
      "Longitude": 103.8466254249,
      "Latitude": 1.4321457667
    },
    {
      "Longitude": 103.77784,
      "Latitude": 1.43218
    },
    {
      "Longitude": 103.77267,
      "Latitude": 1.43223
    },
    {
      "Longitude": 103.7741658837,
      "Latitude": 1.4323210614
    },
    {
      "Longitude": 103.7735633925,
      "Latitude": 1.4323374848
    },
    {
      "Longitude": 103.80181,
      "Latitude": 1.43296
    },
    {
      "Longitude": 103.8019,
      "Latitude": 1.43304
    },
    {
      "Longitude": 103.8414091989,
      "Latitude": 1.433482765
    },
    {
      "Longitude": 103.84174,
      "Latitude": 1.43373
    },
    {
      "Longitude": 103.83476,
      "Latitude": 1.4342
    },
    {
      "Longitude": 103.83346,
      "Latitude": 1.43437
    },
    {
      "Longitude": 103.75842,
      "Latitude": 1.43458
    },
    {
      "Longitude": 103.7750992924,
      "Latitude": 1.4347731738
    },
    {
      "Longitude": 103.8024377078,
      "Latitude": 1.4348388673
    },
    {
      "Longitude": 103.82895,
      "Latitude": 1.43486
    },
    {
      "Longitude": 103.78924,
      "Latitude": 1.43516
    },
    {
      "Longitude": 103.78544,
      "Latitude": 1.43532
    },
    {
      "Longitude": 103.83768,
      "Latitude": 1.43572
    },
    {
      "Longitude": 103.83753,
      "Latitude": 1.43573
    },
    {
      "Longitude": 103.79585,
      "Latitude": 1.43615
    },
    {
      "Longitude": 103.8337229937,
      "Latitude": 1.4368260953
    },
    {
      "Longitude": 103.833844699,
      "Latitude": 1.436839167
    },
    {
      "Longitude": 103.84069,
      "Latitude": 1.43711
    },
    {
      "Longitude": 103.83311,
      "Latitude": 1.43792
    },
    {
      "Longitude": 103.78291,
      "Latitude": 1.43801
    },
    {
      "Longitude": 103.80121,
      "Latitude": 1.44112
    },
    {
      "Longitude": 103.83927,
      "Latitude": 1.44114
    },
    {
      "Longitude": 103.83114,
      "Latitude": 1.44139
    },
    {
      "Longitude": 103.80177,
      "Latitude": 1.44175
    },
    {
      "Longitude": 103.83053,
      "Latitude": 1.44242
    },
    {
      "Longitude": 103.80138,
      "Latitude": 1.44274
    },
    {
      "Longitude": 103.78772,
      "Latitude": 1.44319
    },
    {
      "Longitude": 103.83597,
      "Latitude": 1.4435
    },
    {
      "Longitude": 103.7939,
      "Latitude": 1.44355
    },
    {
      "Longitude": 103.7779276818,
      "Latitude": 1.444029908
    },
    {
      "Longitude": 103.7918651104,
      "Latitude": 1.4442001742
    },
    {
      "Longitude": 103.77678,
      "Latitude": 1.44476
    },
    {
      "Longitude": 103.77696,
      "Latitude": 1.44496
    },
    {
      "Longitude": 103.82283,
      "Latitude": 1.44509
    },
    {
      "Longitude": 103.80987,
      "Latitude": 1.4467
    },
    {
      "Longitude": 103.8276645541,
      "Latitude": 1.446852705
    },
    {
      "Longitude": 103.8140852004,
      "Latitude": 1.4480318301
    },
    {
      "Longitude": 103.80051,
      "Latitude": 1.44832
    },
    {
      "Longitude": 103.81785,
      "Latitude": 1.44892
    },
    {
      "Longitude": 103.82042896,
      "Latitude": 1.4494955129
    },
    {
      "Longitude": 103.8215615228,
      "Latitude": 1.4497552687
    },
    {
      "Longitude": 103.81509,
      "Latitude": 1.44988
    },
    {
      "Longitude": 103.83076,
      "Latitude": 1.45046
    },
    {
      "Longitude": 103.8264461607,
      "Latitude": 1.450639779
    },
    {
      "Longitude": 103.79044,
      "Latitude": 1.45169
    },
    {
      "Longitude": 103.8200504333,
      "Latitude": 1.4519633597
    },
    {
      "Longitude": 103.79072,
      "Latitude": 1.45206
    },
    {
      "Longitude": 103.82145,
      "Latitude": 1.45251
    },
    {
      "Longitude": 103.8023042679,
      "Latitude": 1.4552828659
    },
    {
      "Longitude": 103.81458,
      "Latitude": 1.45744
    },
    {
      "Longitude": 103.82966,
      "Latitude": 1.45754
    },
    {
      "Longitude": 103.79934,
      "Latitude": 1.45818
    },
    {
      "Longitude": 103.8162815943,
      "Latitude": 1.4625261695
    },
    {
      "Longitude": 103.8152623549,
      "Latitude": 1.4638343256
    }
  ],
  "last_updated": "2025-09-15T01:09:22+00:00"
}
