{
  "odata.metadata": "https://datamall2.mytransport.sg/ltaodataservice/$metadata#TaxiAvailability",
  "value": [
    {
      "Longitude": 103.6144949868,
      "Latitude": 1.2464053481
    },
    {
      "Longitude": 103.82976,
      "Latitude": 1.24806
    },
    {
      "Longitude": 103.82544,
      "Latitude": 1.25375
    },
    {
      "Longitude": 103.82585,
      "Latitude": 1.25407
    },
    {
      "Longitude": 103.82562,
      "Latitude": 1.25447
    },
    {
      "Longitude": 103.82064,
      "Latitude": 1.26444
    },
    {
      "Longitude": 103.8201664388,
      "Latitude": 1.2658822209
    },
    {
      "Longitude": 103.82068,
      "Latitude": 1.26646
    },
    {
      "Longitude": 103.81411,
      "Latitude": 1.26944
    },
    {
      "Longitude": 103.8114164025,
      "Latitude": 1.2706795172
    },
    {
      "Longitude": 103.80081,
      "Latitude": 1.27288
    },
    {
      "Longitude": 103.8074058294,
      "Latitude": 1.2729380513
    },
    {
      "Longitude": 103.8261038437,
      "Latitude": 1.2741678755
    },
    {
      "Longitude": 103.8150491193,
      "Latitude": 1.2752921133
    },
    {
      "Longitude": 103.84311,
      "Latitude": 1.27564
    },
    {
      "Longitude": 103.8097614795,
      "Latitude": 1.2757288699
    },
    {
      "Longitude": 103.8468,
      "Latitude": 1.27617
    },
    {
      "Longitude": 103.81935,
      "Latitude": 1.27691
    },
    {
      "Longitude": 103.81904,
      "Latitude": 1.27752
    },
    {
      "Longitude": 103.83057,
      "Latitude": 1.27752
    },
    {
      "Longitude": 103.83619,
      "Latitude": 1.27781
    },
    {
      "Longitude": 103.84787,
      "Latitude": 1.27785
    },
    {
      "Longitude": 103.7130732089,
      "Latitude": 1.2779190202
    },
    {
      "Longitude": 103.8342336193,
      "Latitude": 1.2779706398
    },
    {
      "Longitude": 103.8175003231,
      "Latitude": 1.2780011424
    },
    {
      "Longitude": 103.82923,
      "Latitude": 1.27821
    },
    {
      "Longitude": 103.8346332684,
      "Latitude": 1.2783189051
    },
    {
      "Longitude": 103.83455,
      "Latitude": 1.27844
    },
    {
      "Longitude": 103.8438667729,
      "Latitude": 1.2785364451
    },
    {
      "Longitude": 103.8503617421,
      "Latitude": 1.2785555511
    },
    {
      "Longitude": 103.8352,
      "Latitude": 1.27907
    },
    {
      "Longitude": 103.833235167,
      "Latitude": 1.2790952112
    },
    {
      "Longitude": 103.8353,
      "Latitude": 1.27922
    },
    {
      "Longitude": 103.8287957758,
      "Latitude": 1.2792929748
    },
    {
      "Longitude": 103.8491597772,
      "Latitude": 1.2793844824
    },
    {
      "Longitude": 103.8399286196,
      "Latitude": 1.2799137514
    },
    {
      "Longitude": 103.82742,
      "Latitude": 1.27995
    },
    {
      "Longitude": 103.85356,
      "Latitude": 1.28027
    },
    {
      "Longitude": 103.8392101228,
      "Latitude": 1.2805000029
    },
    {
      "Longitude": 103.84457,
      "Latitude": 1.28091
    },
    {
      "Longitude": 103.844503127,
      "Latitude": 1.2809159767
    },
    {
      "Longitude": 103.844059892,
      "Latitude": 1.2810869247
    },
    {
      "Longitude": 103.8660700992,
      "Latitude": 1.281110053
    },
    {
      "Longitude": 103.85866,
      "Latitude": 1.28124
    },
    {
      "Longitude": 103.86576,
      "Latitude": 1.28128
    },
    {
      "Longitude": 103.83135,
      "Latitude": 1.28141
    },
    {
      "Longitude": 103.83753,
      "Latitude": 1.28144
    },
    {
      "Longitude": 103.83738,
      "Latitude": 1.28148
    },
    {
      "Longitude": 103.80962,
      "Latitude": 1.28151
    },
    {
      "Longitude": 103.83745,
      "Latitude": 1.28155
    },
    {
      "Longitude": 103.8243986294,
      "Latitude": 1.2815525068
    },
    {
      "Longitude": 103.82837,
      "Latitude": 1.28158
    },
    {
      "Longitude": 103.8411389664,
      "Latitude": 1.2817043489
    },
    {
      "Longitude": 103.81692,
      "Latitude": 1.28264
    },
    {
      "Longitude": 103.81696,
      "Latitude": 1.28274
    },
    {
      "Longitude": 103.83598,
      "Latitude": 1.28291
    },
    {
      "Longitude": 103.78783,
      "Latitude": 1.2832
    },
    {
      "Longitude": 103.83694,
      "Latitude": 1.28447
    },
    {
      "Longitude": 103.720205538,
      "Latitude": 1.2847599596
    },
    {
      "Longitude": 103.8437621668,
      "Latitude": 1.2848417464
    },
    {
      "Longitude": 103.84541,
      "Latitude": 1.28495
    },
    {
      "Longitude": 103.84409,
      "Latitude": 1.2851
    },
    {
      "Longitude": 103.81028,
      "Latitude": 1.28535
    },
    {
      "Longitude": 103.84276,
      "Latitude": 1.28582
    },
    {
      "Longitude": 103.8098,
      "Latitude": 1.28603
    },
    {
      "Longitude": 103.85354,
      "Latitude": 1.28612
    },
    {
      "Longitude": 103.84429,
      "Latitude": 1.28618
    },
    {
      "Longitude": 103.80928,
      "Latitude": 1.28625
    },
    {
      "Longitude": 103.83491,
      "Latitude": 1.28632
    },
    {
      "Longitude": 103.84737,
      "Latitude": 1.28664
    },
    {
      "Longitude": 103.83292,
      "Latitude": 1.28685
    },
    {
      "Longitude": 103.8164240867,
      "Latitude": 1.2872340094
    },
    {
      "Longitude": 103.7759146839,
      "Latitude": 1.2873027236
    },
    {
      "Longitude": 103.81002,
      "Latitude": 1.28731
    },
    {
      "Longitude": 103.83202,
      "Latitude": 1.28742
    },
    {
      "Longitude": 103.80716,
      "Latitude": 1.28745
    },
    {
      "Longitude": 103.84135,
      "Latitude": 1.28814
    },
    {
      "Longitude": 103.82949,
      "Latitude": 1.28841
    },
    {
      "Longitude": 103.8197584078,
      "Latitude": 1.288452095
    },
    {
      "Longitude": 103.8461302221,
      "Latitude": 1.2885352225
    },
    {
      "Longitude": 103.7793770805,
      "Latitude": 1.2885995792
    },
    {
      "Longitude": 103.77808,
      "Latitude": 1.28862
    },
    {
      "Longitude": 103.83398,
      "Latitude": 1.28884
    },
    {
      "Longitude": 103.83447,
      "Latitude": 1.28942
    },
    {
      "Longitude": 103.8495433331,
      "Latitude": 1.2894727525
    },
    {
      "Longitude": 103.79228,
      "Latitude": 1.28957
    },
    {
      "Longitude": 103.83331,
      "Latitude": 1.2896
    },
    {
      "Longitude": 103.8345,
      "Latitude": 1.28967
    },
    {
      "Longitude": 103.8338711858,
      "Latitude": 1.2897107383
    },
    {
      "Longitude": 103.80674,
      "Latitude": 1.2902
    },
    {
      "Longitude": 103.82465,
      "Latitude": 1.29034
    },
    {
      "Longitude": 103.85789,
      "Latitude": 1.29034
    },
    {
      "Longitude": 103.8298673183,
      "Latitude": 1.2904200027
    },
    {
      "Longitude": 103.79047,
      "Latitude": 1.29071
    },
    {
      "Longitude": 103.84675,
      "Latitude": 1.29073
    },
    {
      "Longitude": 103.83977,
      "Latitude": 1.29137
    },
    {
      "Longitude": 103.7745588273,
      "Latitude": 1.2922819886
    },
    {
      "Longitude": 103.8499010727,
      "Latitude": 1.2923473508
    },
    {
      "Longitude": 103.8074775785,
      "Latitude": 1.2928903599
    },
    {
      "Longitude": 103.85371,
      "Latitude": 1.29299
    },
    {
      "Longitude": 103.7850110605,
      "Latitude": 1.2935188425
    },
    {
      "Longitude": 103.77688,
      "Latitude": 1.29376
    },
    {
      "Longitude": 103.8272276893,
      "Latitude": 1.2939160435
    },
    {
      "Longitude": 103.78432,
      "Latitude": 1.29399
    },
    {
      "Longitude": 103.80526,
      "Latitude": 1.29426
    },
    {
      "Longitude": 103.82434,
      "Latitude": 1.29427
    },
    {
      "Longitude": 103.78453,
      "Latitude": 1.29435
    },
    {
      "Longitude": 103.78435,
      "Latitude": 1.29463
    },
    {
      "Longitude": 103.784349896,
      "Latitude": 1.2946635185
    },
    {
      "Longitude": 103.784,
      "Latitude": 1.29468
    },
    {
      "Longitude": 103.83735,
      "Latitude": 1.29468
    },
    {
      "Longitude": 103.78429,
      "Latitude": 1.29476
    },
    {
      "Longitude": 103.78422,
      "Latitude": 1.29494
    },
    {
      "Longitude": 103.89165,
      "Latitude": 1.29504
    },
    {
      "Longitude": 103.8438630849,
      "Latitude": 1.2959969061
    },
    {
      "Longitude": 103.86263,
      "Latitude": 1.29648
    },
    {
      "Longitude": 103.80473,
      "Latitude": 1.29686
    },
    {
      "Longitude": 103.8437869772,
      "Latitude": 1.2969173386
    },
    {
      "Longitude": 103.80177,
      "Latitude": 1.29764
    },
    {
      "Longitude": 103.8005363569,
      "Latitude": 1.2980023492
    },
    {
      "Longitude": 103.85208,
      "Latitude": 1.29823
    },
    {
      "Longitude": 103.8021,
      "Latitude": 1.29828
    },
    {
      "Longitude": 103.85434,
      "Latitude": 1.29835
    },
    {
      "Longitude": 103.89549,
      "Latitude": 1.29849
    },
    {
      "Longitude": 103.82993,
      "Latitude": 1.29899
    },
    {
      "Longitude": 103.85327,
      "Latitude": 1.29937
    },
    {
      "Longitude": 103.80111,
      "Latitude": 1.29976
    },
    {
      "Longitude": 103.76299,
      "Latitude": 1.29978
    },
    {
      "Longitude": 103.83656,
      "Latitude": 1.29991
    },
    {
      "Longitude": 103.83837,
      "Latitude": 1.29996
    },
    {
      "Longitude": 103.8542935252,
      "Latitude": 1.3002779537
    },
    {
      "Longitude": 103.7977652997,
      "Latitude": 1.3002796297
    },
    {
      "Longitude": 103.84566,
      "Latitude": 1.30037
    },
    {
      "Longitude": 103.83713,
      "Latitude": 1.30048
    },
    {
      "Longitude": 103.849774003,
      "Latitude": 1.3004975031
    },
    {
      "Longitude": 103.85101,
      "Latitude": 1.30099
    },
    {
      "Longitude": 103.90314,
      "Latitude": 1.30116
    },
    {
      "Longitude": 103.7751794234,
      "Latitude": 1.3019777006
    },
    {
      "Longitude": 103.86513,
      "Latitude": 1.30199
    },
    {
      "Longitude": 103.8649308309,
      "Latitude": 1.301996136
    },
    {
      "Longitude": 103.8345118985,
      "Latitude": 1.3020628388
    },
    {
      "Longitude": 103.83424,
      "Latitude": 1.30211
    },
    {
      "Longitude": 103.84171,
      "Latitude": 1.30228
    },
    {
      "Longitude": 103.83267,
      "Latitude": 1.3024
    },
    {
      "Longitude": 103.85726,
      "Latitude": 1.30244
    },
    {
      "Longitude": 103.84119,
      "Latitude": 1.30254
    },
    {
      "Longitude": 103.8528891,
      "Latitude": 1.3025615
    },
    {
      "Longitude": 103.79796,
      "Latitude": 1.30258
    },
    {
      "Longitude": 103.7834282219,
      "Latitude": 1.3029286332
    },
    {
      "Longitude": 103.84066,
      "Latitude": 1.30321
    },
    {
      "Longitude": 103.8566,
      "Latitude": 1.30329
    },
    {
      "Longitude": 103.85626,
      "Latitude": 1.30335
    },
    {
      "Longitude": 103.85621,
      "Latitude": 1.3034
    },
    {
      "Longitude": 103.83357,
      "Latitude": 1.30388
    },
    {
      "Longitude": 103.7965,
      "Latitude": 1.30393
    },
    {
      "Longitude": 103.86274,
      "Latitude": 1.30398
    },
    {
      "Longitude": 103.83351,
      "Latitude": 1.30409
    },
    {
      "Longitude": 103.91956,
      "Latitude": 1.30415
    },
    {
      "Longitude": 103.82528,
      "Latitude": 1.3042
    },
    {
      "Longitude": 103.83277,
      "Latitude": 1.30442
    },
    {
      "Longitude": 103.85481,
      "Latitude": 1.30469
    },
    {
      "Longitude": 103.78925,
      "Latitude": 1.30511
    },
    {
      "Longitude": 103.8318,
      "Latitude": 1.30529
    },
    {
      "Longitude": 103.91471,
      "Latitude": 1.30533
    },
    {
      "Longitude": 103.82468,
      "Latitude": 1.30547
    },
    {
      "Longitude": 103.86207,
      "Latitude": 1.30551
    },
    {
      "Longitude": 103.87107,
      "Latitude": 1.30553
    },
    {
      "Longitude": 103.8824805245,
      "Latitude": 1.3056761796
    },
    {
      "Longitude": 103.88246,
      "Latitude": 1.30575
    },
    {
      "Longitude": 103.79377,
      "Latitude": 1.30618
    },
    {
      "Longitude": 103.864,
      "Latitude": 1.30629
    },
    {
      "Longitude": 103.8282988966,
      "Latitude": 1.3064977279
    },
    {
      "Longitude": 103.79957,
      "Latitude": 1.30677
    },
    {
      "Longitude": 103.84041,
      "Latitude": 1.30683
    },
    {
      "Longitude": 103.8588,
      "Latitude": 1.30687
    },
    {
      "Longitude": 103.85819,
      "Latitude": 1.30737
    },
    {
      "Longitude": 103.79975,
      "Latitude": 1.30761
    },
    {
      "Longitude": 103.85599,
      "Latitude": 1.30783
    },
    {
      "Longitude": 103.85283,
      "Latitude": 1.30791
    },
    {
      "Longitude": 103.8637667522,
      "Latitude": 1.3081807111
    },
    {
      "Longitude": 103.8876350597,
      "Latitude": 1.3082028336
    },
    {
      "Longitude": 103.90828,
      "Latitude": 1.3083
    },
    {
      "Longitude": 103.87767,
      "Latitude": 1.30884
    },
    {
      "Longitude": 103.7846808136,
      "Latitude": 1.3088681831
    },
    {
      "Longitude": 103.87616,
      "Latitude": 1.309
    },
    {
      "Longitude": 103.8535297662,
      "Latitude": 1.3091242672
    },
    {
      "Longitude": 103.85787,
      "Latitude": 1.30915
    },
    {
      "Longitude": 103.8430798799,
      "Latitude": 1.3093304082
    },
    {
      "Longitude": 103.82795,
      "Latitude": 1.30989
    },
    {
      "Longitude": 103.80173,
      "Latitude": 1.30994
    },
    {
      "Longitude": 103.90199,
      "Latitude": 1.31005
    },
    {
      "Longitude": 103.8278432563,
      "Latitude": 1.3100996659
    },
    {
      "Longitude": 103.90182,
      "Latitude": 1.31021
    },
    {
      "Longitude": 103.8630365208,
      "Latitude": 1.3104375359
    },
    {
      "Longitude": 103.84781,
      "Latitude": 1.31045
    },
    {
      "Longitude": 103.87211,
      "Latitude": 1.31053
    },
    {
      "Longitude": 103.8357654959,
      "Latitude": 1.3107636742
    },
    {
      "Longitude": 103.84748,
      "Latitude": 1.31108
    },
    {
      "Longitude": 103.93239,
      "Latitude": 1.31126
    },
    {
      "Longitude": 103.87816,
      "Latitude": 1.31128
    },
    {
      "Longitude": 103.8005356863,
      "Latitude": 1.3116418676
    },
    {
      "Longitude": 103.88066,
      "Latitude": 1.31174
    },
    {
      "Longitude": 103.7607,
      "Latitude": 1.31187
    },
    {
      "Longitude": 103.78788,
      "Latitude": 1.31187
    },
    {
      "Longitude": 103.7681034207,
      "Latitude": 1.311877505
    },
    {
      "Longitude": 103.78837,
      "Latitude": 1.31209
    },
    {
      "Longitude": 103.86174,
      "Latitude": 1.3122
    },
    {
      "Longitude": 103.77189,
      "Latitude": 1.31232
    },
    {
      "Longitude": 103.76806,
      "Latitude": 1.31239
    },
    {
      "Longitude": 103.8538600132,
      "Latitude": 1.313085188
    },
    {
      "Longitude": 103.88228,
      "Latitude": 1.31316
    },
    {
      "Longitude": 103.85448,
      "Latitude": 1.31335
    },
    {
      "Longitude": 103.87138,
      "Latitude": 1.31335
    },
    {
      "Longitude": 103.765954636,
      "Latitude": 1.3133593718
    },
    {
      "Longitude": 103.88214,
      "Latitude": 1.31348
    },
    {
      "Longitude": 103.8841,
      "Latitude": 1.3135
    },
    {
      "Longitude": 103.8738361001,
      "Latitude": 1.3135537809
    },
    {
      "Longitude": 103.89409,
      "Latitude": 1.31375
    },
    {
      "Longitude": 103.85723,
      "Latitude": 1.31412
    },
    {
      "Longitude": 103.7642514333,
      "Latitude": 1.3141373431
    },
    {
      "Longitude": 103.87784,
      "Latitude": 1.31422
    },
    {
      "Longitude": 103.8856881112,
      "Latitude": 1.3143267243
    },
    {
      "Longitude": 103.88183,
      "Latitude": 1.31445
    },
    {
      "Longitude": 103.89415,
      "Latitude": 1.31465
    },
    {
      "Longitude": 103.89847,
      "Latitude": 1.31493
    },
    {
      "Longitude": 103.75272,
      "Latitude": 1.315
    },
    {
      "Longitude": 103.89411,
      "Latitude": 1.31513
    },
    {
      "Longitude": 103.76477,
      "Latitude": 1.31514
    },
    {
      "Longitude": 103.8348310813,
      "Latitude": 1.3155454673
    },
    {
      "Longitude": 103.8991896808,
      "Latitude": 1.3155498247
    },
    {
      "Longitude": 103.9597955346,
      "Latitude": 1.3156590959
    },
    {
      "Longitude": 103.88564,
      "Latitude": 1.3157
    },
    {
      "Longitude": 103.89045,
      "Latitude": 1.31676
    },
    {
      "Longitude": 103.7661195919,
      "Latitude": 1.3170001817
    },
    {
      "Longitude": 103.8498594984,
      "Latitude": 1.3171453179
    },
    {
      "Longitude": 103.87935,
      "Latitude": 1.3175
    },
    {
      "Longitude": 103.89771346,
      "Latitude": 1.3177577055
    },
    {
      "Longitude": 103.8889423013,
      "Latitude": 1.3179199362
    },
    {
      "Longitude": 103.8858,
      "Latitude": 1.31814
    },
    {
      "Longitude": 103.90001,
      "Latitude": 1.31823
    },
    {
      "Longitude": 103.85503,
      "Latitude": 1.3184
    },
    {
      "Longitude": 103.74896,
      "Latitude": 1.31842
    },
    {
      "Longitude": 103.88214,
      "Latitude": 1.3185
    },
    {
      "Longitude": 103.89308,
      "Latitude": 1.3186
    },
    {
      "Longitude": 103.8823940232,
      "Latitude": 1.3186157852
    },
    {
      "Longitude": 103.9117,
      "Latitude": 1.31891
    },
    {
      "Longitude": 103.8901368901,
      "Latitude": 1.3189596874
    },
    {
      "Longitude": 103.86232,
      "Latitude": 1.31905
    },
    {
      "Longitude": 103.8519046828,
      "Latitude": 1.3192502948
    },
    {
      "Longitude": 103.7629066408,
      "Latitude": 1.3194587812
    },
    {
      "Longitude": 103.8530949131,
      "Latitude": 1.3195945321
    },
    {
      "Longitude": 103.8618757948,
      "Latitude": 1.3199320656
    },
    {
      "Longitude": 103.8623401523,
      "Latitude": 1.3200302754
    },
    {
      "Longitude": 103.8620736077,
      "Latitude": 1.3201898245
    },
    {
      "Longitude": 103.88782,
      "Latitude": 1.32044
    },
    {
      "Longitude": 103.8880803064,
      "Latitude": 1.320477415
    },
    {
      "Longitude": 103.8549463078,
      "Latitude": 1.3205199838
    },
    {
      "Longitude": 103.84257,
      "Latitude": 1.32068
    },
    {
      "Longitude": 103.87121,
      "Latitude": 1.32126
    },
    {
      "Longitude": 103.8828687742,
      "Latitude": 1.3213173937
    },
    {
      "Longitude": 103.85289,
      "Latitude": 1.32206
    },
    {
      "Longitude": 103.74127,
      "Latitude": 1.3221
    },
    {
      "Longitude": 103.8889221847,
      "Latitude": 1.3224158012
    },
    {
      "Longitude": 103.85507,
      "Latitude": 1.32258
    },
    {
      "Longitude": 103.8822039217,
      "Latitude": 1.3231706418
    },
    {
      "Longitude": 103.8875716925,
      "Latitude": 1.3236214679
    },
    {
      "Longitude": 103.8514587656,
      "Latitude": 1.3242804448
    },
    {
      "Longitude": 103.8881,
      "Latitude": 1.32439
    },
    {
      "Longitude": 103.93291,
      "Latitude": 1.3245
    },
    {
      "Longitude": 103.94439,
      "Latitude": 1.32458
    },
    {
      "Longitude": 103.774587661,
      "Latitude": 1.3253225397
    },
    {
      "Longitude": 103.77465,
      "Latitude": 1.32534
    },
    {
      "Longitude": 103.77504,
      "Latitude": 1.32562
    },
    {
      "Longitude": 103.916233778,
      "Latitude": 1.3258809602
    },
    {
      "Longitude": 103.75624,
      "Latitude": 1.32634
    },
    {
      "Longitude": 103.89017,
      "Latitude": 1.32651
    },
    {
      "Longitude": 103.8751872629,
      "Latitude": 1.3267795947
    },
    {
      "Longitude": 103.72324,
      "Latitude": 1.32709
    },
    {
      "Longitude": 103.70845,
      "Latitude": 1.32763
    },
    {
      "Longitude": 103.8564030826,
      "Latitude": 1.3279028035
    },
    {
      "Longitude": 103.93952,
      "Latitude": 1.32806
    },
    {
      "Longitude": 103.8685860112,
      "Latitude": 1.3297037577
    },
    {
      "Longitude": 103.74629,
      "Latitude": 1.33187
    },
    {
      "Longitude": 103.966335766,
      "Latitude": 1.3319977685
    },
    {
      "Longitude": 103.95493,
      "Latitude": 1.33237
    },
    {
      "Longitude": 103.92767,
      "Latitude": 1.33339
    },
    {
      "Longitude": 103.80817,
      "Latitude": 1.3334
    },
    {
      "Longitude": 103.81219,
      "Latitude": 1.33413
    },
    {
      "Longitude": 103.8699703664,
      "Latitude": 1.3345210439
    },
    {
      "Longitude": 103.70283,
      "Latitude": 1.33487
    },
    {
      "Longitude": 103.7456513196,
      "Latitude": 1.3350489605
    },
    {
      "Longitude": 103.86198,
      "Latitude": 1.33576
    },
    {
      "Longitude": 103.70921,
      "Latitude": 1.33604
    },
    {
      "Longitude": 103.8658,
      "Latitude": 1.3361
    },
    {
      "Longitude": 103.98173,
      "Latitude": 1.33616
    },
    {
      "Longitude": 103.98205,
      "Latitude": 1.33626
    },
    {
      "Longitude": 103.78289,
      "Latitude": 1.33632
    },
    {
      "Longitude": 103.91358,
      "Latitude": 1.3366
    },
    {
      "Longitude": 103.87314,
      "Latitude": 1.33666
    },
    {
      "Longitude": 103.96752,
      "Latitude": 1.33715
    },
    {
      "Longitude": 103.9813886583,
      "Latitude": 1.3371616314
    },
    {
      "Longitude": 103.9237784967,
      "Latitude": 1.3373979367
    },
    {
      "Longitude": 103.98151,
      "Latitude": 1.33753
    },
    {
      "Longitude": 103.85623,
      "Latitude": 1.33816
    },
    {
      "Longitude": 103.84487,
      "Latitude": 1.33836
    },
    {
      "Longitude": 103.98104,
      "Latitude": 1.33874
    },
    {
      "Longitude": 103.70693,
      "Latitude": 1.33885
    },
    {
      "Longitude": 103.70697,
      "Latitude": 1.33889
    },
    {
      "Longitude": 103.74222,
      "Latitude": 1.33894
    },
    {
      "Longitude": 103.72234,
      "Latitude": 1.33912
    },
    {
      "Longitude": 103.71514,
      "Latitude": 1.33939
    },
    {
      "Longitude": 103.98274,
      "Latitude": 1.33945
    },
    {
      "Longitude": 103.7383862,
      "Latitude": 1.34014504
    },
    {
      "Longitude": 103.7090633065,
      "Latitude": 1.340383761
    },
    {
      "Longitude": 103.85031,
      "Latitude": 1.34055
    },
    {
      "Longitude": 103.8882,
      "Latitude": 1.34092
    },
    {
      "Longitude": 103.85974,
      "Latitude": 1.34131
    },
    {
      "Longitude": 103.74219,
      "Latitude": 1.34134
    },
    {
      "Longitude": 103.6908,
      "Latitude": 1.34136
    },
    {
      "Longitude": 103.835375905,
      "Latitude": 1.3416014855
    },
    {
      "Longitude": 103.6899525672,
      "Latitude": 1.3417801387
    },
    {
      "Longitude": 103.85836,
      "Latitude": 1.34185
    },
    {
      "Longitude": 103.88188,
      "Latitude": 1.34186
    },
    {
      "Longitude": 103.8582,
      "Latitude": 1.34203
    },
    {
      "Longitude": 103.86947,
      "Latitude": 1.34263
    },
    {
      "Longitude": 103.85781,
      "Latitude": 1.34281
    },
    {
      "Longitude": 103.75804,
      "Latitude": 1.34288
    },
    {
      "Longitude": 103.85689,
      "Latitude": 1.34313
    },
    {
      "Longitude": 103.69594,
      "Latitude": 1.34315
    },
    {
      "Longitude": 103.8554,
      "Latitude": 1.34316
    },
    {
      "Longitude": 103.85172,
      "Latitude": 1.34341
    },
    {
      "Longitude": 103.85609,
      "Latitude": 1.34446
    },
    {
      "Longitude": 103.71694,
      "Latitude": 1.34487
    },
    {
      "Longitude": 103.87246,
      "Latitude": 1.34588
    },
    {
      "Longitude": 103.95771,
      "Latitude": 1.34635
    },
    {
      "Longitude": 103.73179,
      "Latitude": 1.34646
    },
    {
      "Longitude": 103.74959,
      "Latitude": 1.34654
    },
    {
      "Longitude": 103.7330486253,
      "Latitude": 1.3465585199
    },
    {
      "Longitude": 103.74581,
      "Latitude": 1.34684
    },
    {
      "Longitude": 103.73026,
      "Latitude": 1.34752
    },
    {
      "Longitude": 103.98484,
      "Latitude": 1.34791
    },
    {
      "Longitude": 103.8401894644,
      "Latitude": 1.348130195
    },
    {
      "Longitude": 103.9419581741,
      "Latitude": 1.3483145459
    },
    {
      "Longitude": 103.72369,
      "Latitude": 1.34853
    },
    {
      "Longitude": 103.9849999174,
      "Latitude": 1.3486416847
    },
    {
      "Longitude": 103.88817,
      "Latitude": 1.34945
    },
    {
      "Longitude": 103.93339,
      "Latitude": 1.34954
    },
    {
      "Longitude": 103.73962,
      "Latitude": 1.34958
    },
    {
      "Longitude": 103.9855,
      "Latitude": 1.34982
    },
    {
      "Longitude": 103.74553,
      "Latitude": 1.35018
    },
    {
      "Longitude": 103.9259983599,
      "Latitude": 1.350333354
    },
    {
      "Longitude": 103.886,
      "Latitude": 1.35035
    },
    {
      "Longitude": 103.9857143909,
      "Latitude": 1.3504473162
    },
    {
      "Longitude": 103.75025,
      "Latitude": 1.35088
    },
    {
      "Longitude": 103.87281,
      "Latitude": 1.35113
    },
    {
      "Longitude": 103.7199101597,
      "Latitude": 1.3511324302
    },
    {
      "Longitude": 103.75535,
      "Latitude": 1.35126
    },
    {
      "Longitude": 103.96778,
      "Latitude": 1.35134
    },
    {
      "Longitude": 103.95136,
      "Latitude": 1.3517
    },
    {
      "Longitude": 103.74658,
      "Latitude": 1.35174
    },
    {
      "Longitude": 103.7374058738,
      "Latitude": 1.3518812287
    },
    {
      "Longitude": 103.98513,
      "Latitude": 1.352
    },
    {
      "Longitude": 103.98512,
      "Latitude": 1.35209
    },
    {
      "Longitude": 103.98701,
      "Latitude": 1.3524
    },
    {
      "Longitude": 103.87377,
      "Latitude": 1.35243
    },
    {
      "Longitude": 103.98569,
      "Latitude": 1.35246
    },
    {
      "Longitude": 103.9858716354,
      "Latitude": 1.352582431
    },
    {
      "Longitude": 103.98576,
      "Latitude": 1.35264
    },
    {
      "Longitude": 103.73954,
      "Latitude": 1.35276
    },
    {
      "Longitude": 103.96463,
      "Latitude": 1.35278
    },
    {
      "Longitude": 103.985975571,
      "Latitude": 1.3528251033
    },
    {
      "Longitude": 103.98589,
      "Latitude": 1.35299
    },
    {
      "Longitude": 103.85694,
      "Latitude": 1.35309
    },
    {
      "Longitude": 103.98595,
      "Latitude": 1.35318
    },
    {
      "Longitude": 103.95807,
      "Latitude": 1.35366
    },
    {
      "Longitude": 103.98622,
      "Latitude": 1.35385
    },
    {
      "Longitude": 103.9878128842,
      "Latitude": 1.3545968783
    },
    {
      "Longitude": 103.74166,
      "Latitude": 1.35467
    },
    {
      "Longitude": 103.98776,
      "Latitude": 1.3548
    },
    {
      "Longitude": 103.95457,
      "Latitude": 1.35483
    },
    {
      "Longitude": 103.832260184,
      "Latitude": 1.3550004379
    },
    {
      "Longitude": 103.87315,
      "Latitude": 1.35515
    },
    {
      "Longitude": 103.844909817,
      "Latitude": 1.3558461029
    },
    {
      "Longitude": 103.89103,
      "Latitude": 1.35595
    },
    {
      "Longitude": 103.9885,
      "Latitude": 1.35595
    },
    {
      "Longitude": 103.7509047613,
      "Latitude": 1.3561799444
    },
    {
      "Longitude": 103.7487727404,
      "Latitude": 1.3565556836
    },
    {
      "Longitude": 103.7444128096,
      "Latitude": 1.3566331107
    },
    {
      "Longitude": 103.9888783917,
      "Latitude": 1.35687109
    },
    {
      "Longitude": 103.93292,
      "Latitude": 1.35702
    },
    {
      "Longitude": 103.8444491476,
      "Latitude": 1.3570484013
    },
    {
      "Longitude": 103.98969,
      "Latitude": 1.35744
    },
    {
      "Longitude": 103.95827,
      "Latitude": 1.35752
    },
    {
      "Longitude": 103.9899,
      "Latitude": 1.35752
    },
    {
      "Longitude": 103.98956,
      "Latitude": 1.3576
    },
    {
      "Longitude": 103.98953,
      "Latitude": 1.35774
    },
    {
      "Longitude": 103.74321,
      "Latitude": 1.35794
    },
    {
      "Longitude": 103.98952,
      "Latitude": 1.35804
    },
    {
      "Longitude": 103.9897822961,
      "Latitude": 1.3581099228
    },
    {
      "Longitude": 103.95104,
      "Latitude": 1.35834
    },
    {
      "Longitude": 103.75148,
      "Latitude": 1.35859
    },
    {
      "Longitude": 103.99014,
      "Latitude": 1.35863
    },
    {
      "Longitude": 103.95541,
      "Latitude": 1.35866
    },
    {
      "Longitude": 103.98967,
      "Latitude": 1.35879
    },
    {
      "Longitude": 103.74249,
      "Latitude": 1.35939
    },
    {
      "Longitude": 103.98952,
      "Latitude": 1.35939
    },
    {
      "Longitude": 103.98851,
      "Latitude": 1.36054
    },
    {
      "Longitude": 103.98904,
      "Latitude": 1.36073
    },
    {
      "Longitude": 103.9891,
      "Latitude": 1.36099
    },
    {
      "Longitude": 103.7510757521,
      "Latitude": 1.3610534888
    },
    {
      "Longitude": 103.9889913797,
      "Latitude": 1.3611976168
    },
    {
      "Longitude": 103.98879,
      "Latitude": 1.36124
    },
    {
      "Longitude": 103.9889,
      "Latitude": 1.36128
    },
    {
      "Longitude": 103.9890899509,
      "Latitude": 1.3613950387
    },
    {
      "Longitude": 103.74418,
      "Latitude": 1.36204
    },
    {
      "Longitude": 103.74161,
      "Latitude": 1.36225
    },
    {
      "Longitude": 103.89286,
      "Latitude": 1.36226
    },
    {
      "Longitude": 103.83922,
      "Latitude": 1.3624
    },
    {
      "Longitude": 103.84901,
      "Latitude": 1.36354
    },
    {
      "Longitude": 103.85929,
      "Latitude": 1.36367
    },
    {
      "Longitude": 103.8662068918,
      "Latitude": 1.3643194954
    },
    {
      "Longitude": 103.9582814276,
      "Latitude": 1.3651286224
    },
    {
      "Longitude": 103.85,
      "Latitude": 1.36575
    },
    {
      "Longitude": 103.8956377655,
      "Latitude": 1.3660161815
    },
    {
      "Longitude": 103.83863,
      "Latitude": 1.36676
    },
    {
      "Longitude": 103.8282670453,
      "Latitude": 1.3677544287
    },
    {
      "Longitude": 103.89579,
      "Latitude": 1.36792
    },
    {
      "Longitude": 103.94453,
      "Latitude": 1.36813
    },
    {
      "Longitude": 103.8445500657,
      "Latitude": 1.3681938504
    },
    {
      "Longitude": 103.85005,
      "Latitude": 1.36832
    },
    {
      "Longitude": 103.83939,
      "Latitude": 1.37044
    },
    {
      "Longitude": 103.7465076149,
      "Latitude": 1.3707643486
    },
    {
      "Longitude": 103.83678,
      "Latitude": 1.37104
    },
    {
      "Longitude": 103.90086,
      "Latitude": 1.37183
    },
    {
      "Longitude": 103.8940834254,
      "Latitude": 1.372622922
    },
    {
      "Longitude": 103.84702,
      "Latitude": 1.37315
    },
    {
      "Longitude": 103.8461761549,
      "Latitude": 1.3735614256
    },
    {
      "Longitude": 103.9014,
      "Latitude": 1.37424
    },
    {
      "Longitude": 103.90239,
      "Latitude": 1.37653
    },
    {
      "Longitude": 103.8371,
      "Latitude": 1.37715
    },
    {
      "Longitude": 103.73743,
      "Latitude": 1.37716
    },
    {
      "Longitude": 103.77247,
      "Latitude": 1.37887
    },
    {
      "Longitude": 103.7680873275,
      "Latitude": 1.3789236258
    },
    {
      "Longitude": 103.93663,
      "Latitude": 1.37938
    },
    {
      "Longitude": 103.77257,
      "Latitude": 1.37959
    },
    {
      "Longitude": 103.88965,
      "Latitude": 1.37978
    },
    {
      "Longitude": 103.7702,
      "Latitude": 1.38
    },
    {
      "Longitude": 103.90394,
      "Latitude": 1.38032
    },
    {
      "Longitude": 103.88027,
      "Latitude": 1.38051
    },
    {
      "Longitude": 103.74996,
      "Latitude": 1.38186
    },
    {
      "Longitude": 103.94137,
      "Latitude": 1.38227
    },
    {
      "Longitude": 103.7641273811,
      "Latitude": 1.3848301434
    },
    {
      "Longitude": 103.90095,
      "Latitude": 1.38558
    },
    {
      "Longitude": 103.89891,
      "Latitude": 1.38571
    },
    {
      "Longitude": 103.9250438288,
      "Latitude": 1.3857803734
    },
    {
      "Longitude": 103.98028,
      "Latitude": 1.38712
    },
    {
      "Longitude": 103.84214,
      "Latitude": 1.38775
    },
    {
      "Longitude": 103.74058,
      "Latitude": 1.38851
    },
    {
      "Longitude": 103.89117,
      "Latitude": 1.38895
    },
    {
      "Longitude": 103.76709,
      "Latitude": 1.38985
    },
    {
      "Longitude": 103.900655508,
      "Latitude": 1.3910376355
    },
    {
      "Longitude": 103.89374,
      "Latitude": 1.39136
    },
    {
      "Longitude": 103.89799,
      "Latitude": 1.39176
    },
    {
      "Longitude": 103.90544,
      "Latitude": 1.39235
    },
    {
      "Longitude": 103.90124,
      "Latitude": 1.39381
    },
    {
      "Longitude": 103.8970251381,
      "Latitude": 1.395924851
    },
    {
      "Longitude": 103.74714,
      "Latitude": 1.39651
    },
    {
      "Longitude": 103.90716,
      "Latitude": 1.39828
    },
    {
      "Longitude": 103.8600153476,
      "Latitude": 1.4024788855
    },
    {
      "Longitude": 103.91029,
      "Latitude": 1.40276
    },
    {
      "Longitude": 103.81903,
      "Latitude": 1.40447
    },
    {
      "Longitude": 103.78924,
      "Latitude": 1.40476
    },
    {
      "Longitude": 103.91012,
      "Latitude": 1.4049
    },
    {
      "Longitude": 103.78903,
      "Latitude": 1.4052
    },
    {
      "Longitude": 103.90532,
      "Latitude": 1.40724
    },
    {
      "Longitude": 103.86109,
      "Latitude": 1.41021
    },
    {
      "Longitude": 103.78114,
      "Latitude": 1.41084
    },
    {
      "Longitude": 103.839263767,
      "Latitude": 1.4137591961
    },
    {
      "Longitude": 103.86164,
      "Latitude": 1.41445
    },
    {
      "Longitude": 103.79476,
      "Latitude": 1.42551
    },
    {
      "Longitude": 103.79481,
      "Latitude": 1.42611
    },
    {
      "Longitude": 103.83676,
      "Latitude": 1.42884
    },
    {
      "Longitude": 103.77522,
      "Latitude": 1.4305
    },
    {
      "Longitude": 103.78008,
      "Latitude": 1.43064
    },
    {
      "Longitude": 103.7727912515,
      "Latitude": 1.433537398
    },
    {
      "Longitude": 103.83285,
      "Latitude": 1.43432
    },
    {
      "Longitude": 103.78561,
      "Latitude": 1.43535
    },
    {
      "Longitude": 103.78528,
      "Latitude": 1.43553
    },
    {
      "Longitude": 103.82578,
      "Latitude": 1.43597
    },
    {
      "Longitude": 103.77658,
      "Latitude": 1.44061
    },
    {
      "Longitude": 103.77975,
      "Latitude": 1.44141
    },
    {
      "Longitude": 103.80441,
      "Latitude": 1.44267
    },
    {
      "Longitude": 103.80165,
      "Latitude": 1.44327
    },
    {
      "Longitude": 103.78787,
      "Latitude": 1.4435
    },
    {
      "Longitude": 103.83604,
      "Latitude": 1.44353
    },
    {
      "Longitude": 103.82557,
      "Latitude": 1.44407
    },
    {
      "Longitude": 103.77779,
      "Latitude": 1.44414
    },
    {
      "Longitude": 103.7968,
      "Latitude": 1.44796
    },
    {
      "Longitude": 103.7969257683,
      "Latitude": 1.4491013543
    },
    {
      "Longitude": 103.7964,
      "Latitude": 1.4547
    }
  ]
}
