{
  "odata.metadata": "https://datamall2.mytransport.sg/ltaodataservice/$metadata#TaxiAvailability",
  "value": [
    {
      "Longitude": 103.82532,
      "Latitude": 1.25385
    },
    {
      "Longitude": 103.825543,
      "Latitude": 1.2540803
    },
    {
      "Longitude": 103.8256,
      "Latitude": 1.25426
    },
    {
      "Longitude": 103.82557,
      "Latitude": 1.25431
    },
    {
      "Longitude": 103.82538,
      "Latitude": 1.25438
    },
    {
      "Longitude": 103.8192038611,
      "Latitude": 1.2547322938
    },
    {
      "Longitude": 103.82438,
      "Latitude": 1.25521
    },
    {
      "Longitude": 103.82392,
      "Latitude": 1.26338
    },
    {
      "Longitude": 103.81788,
      "Latitude": 1.26517
    },
    {
      "Longitude": 103.81477,
      "Latitude": 1.26906
    },
    {
      "Longitude": 103.86085,
      "Latitude": 1.27041
    },
    {
      "Longitude": 103.854800798,
      "Latitude": 1.2721174977
    },
    {
      "Longitude": 103.83808,
      "Latitude": 1.27263
    },
    {
      "Longitude": 103.84631,
      "Latitude": 1.27354
    },
    {
      "Longitude": 103.86654,
      "Latitude": 1.27539
    },
    {
      "Longitude": 103.8463987783,
      "Latitude": 1.2756896523
    },
    {
      "Longitude": 103.86785,
      "Latitude": 1.27606
    },
    {
      "Longitude": 103.834982,
      "Latitude": 1.2760717
    },
    {
      "Longitude": 103.832008,
      "Latitude": 1.2762098
    },
    {
      "Longitude": 103.80948,
      "Latitude": 1.2763
    },
    {
      "Longitude": 103.8094563782,
      "Latitude": 1.2763563511
    },
    {
      "Longitude": 103.83092,
      "Latitude": 1.27708
    },
    {
      "Longitude": 103.8026633486,
      "Latitude": 1.2772503106
    },
    {
      "Longitude": 103.8632408,
      "Latitude": 1.2777646
    },
    {
      "Longitude": 103.7166,
      "Latitude": 1.27854
    },
    {
      "Longitude": 103.85231,
      "Latitude": 1.27882
    },
    {
      "Longitude": 103.8419697,
      "Latitude": 1.2790924
    },
    {
      "Longitude": 103.83547,
      "Latitude": 1.27928
    },
    {
      "Longitude": 103.8646786,
      "Latitude": 1.2797734
    },
    {
      "Longitude": 103.85782,
      "Latitude": 1.28007
    },
    {
      "Longitude": 103.827,
      "Latitude": 1.2804
    },
    {
      "Longitude": 103.85089,
      "Latitude": 1.28046
    },
    {
      "Longitude": 103.82436,
      "Latitude": 1.28055
    },
    {
      "Longitude": 103.85074,
      "Latitude": 1.28063
    },
    {
      "Longitude": 103.84345,
      "Latitude": 1.2807
    },
    {
      "Longitude": 103.85458,
      "Latitude": 1.28076
    },
    {
      "Longitude": 103.85015,
      "Latitude": 1.28085
    },
    {
      "Longitude": 103.8444954157,
      "Latitude": 1.2809052505
    },
    {
      "Longitude": 103.86602,
      "Latitude": 1.28112
    },
    {
      "Longitude": 103.86037,
      "Latitude": 1.28134
    },
    {
      "Longitude": 103.84514,
      "Latitude": 1.28147
    },
    {
      "Longitude": 103.84931,
      "Latitude": 1.28163
    },
    {
      "Longitude": 103.85081,
      "Latitude": 1.28185
    },
    {
      "Longitude": 103.859343119,
      "Latitude": 1.2824105989
    },
    {
      "Longitude": 103.85188,
      "Latitude": 1.28246
    },
    {
      "Longitude": 103.85209,
      "Latitude": 1.28257
    },
    {
      "Longitude": 103.85157,
      "Latitude": 1.28275
    },
    {
      "Longitude": 103.85992,
      "Latitude": 1.28278
    },
    {
      "Longitude": 103.8603184372,
      "Latitude": 1.2830467935
    },
    {
      "Longitude": 103.85967,
      "Latitude": 1.2831
    },
    {
      "Longitude": 103.8606,
      "Latitude": 1.28331
    },
    {
      "Longitude": 103.84214,
      "Latitude": 1.28338
    },
    {
      "Longitude": 103.83692,
      "Latitude": 1.28389
    },
    {
      "Longitude": 103.82164,
      "Latitude": 1.2847
    },
    {
      "Longitude": 103.84595,
      "Latitude": 1.28519
    },
    {
      "Longitude": 103.84484,
      "Latitude": 1.2857282
    },
    {
      "Longitude": 103.84191,
      "Latitude": 1.28592
    },
    {
      "Longitude": 103.84793,
      "Latitude": 1.28671
    },
    {
      "Longitude": 103.846579,
      "Latitude": 1.2876524
    },
    {
      "Longitude": 103.82947,
      "Latitude": 1.28796
    },
    {
      "Longitude": 103.79463,
      "Latitude": 1.28805
    },
    {
      "Longitude": 103.81713,
      "Latitude": 1.28866
    },
    {
      "Longitude": 103.83794,
      "Latitude": 1.28866
    },
    {
      "Longitude": 103.8412063,
      "Latitude": 1.2887758
    },
    {
      "Longitude": 103.8385143,
      "Latitude": 1.2889095
    },
    {
      "Longitude": 103.86061,
      "Latitude": 1.28953
    },
    {
      "Longitude": 103.79178,
      "Latitude": 1.28986
    },
    {
      "Longitude": 103.85634,
      "Latitude": 1.28988
    },
    {
      "Longitude": 103.86361,
      "Latitude": 1.28994
    },
    {
      "Longitude": 103.8579121605,
      "Latitude": 1.2903197806
    },
    {
      "Longitude": 103.86082,
      "Latitude": 1.29059
    },
    {
      "Longitude": 103.78593,
      "Latitude": 1.29069
    },
    {
      "Longitude": 103.8449396566,
      "Latitude": 1.2908229024
    },
    {
      "Longitude": 103.85876,
      "Latitude": 1.29154
    },
    {
      "Longitude": 103.8548,
      "Latitude": 1.29162
    },
    {
      "Longitude": 103.8153719902,
      "Latitude": 1.2916581983
    },
    {
      "Longitude": 103.8590963557,
      "Latitude": 1.2920202045
    },
    {
      "Longitude": 103.8609261,
      "Latitude": 1.2921413
    },
    {
      "Longitude": 103.8537919521,
      "Latitude": 1.2925028794
    },
    {
      "Longitude": 103.82577,
      "Latitude": 1.29254
    },
    {
      "Longitude": 103.84975,
      "Latitude": 1.29261
    },
    {
      "Longitude": 103.8495792076,
      "Latitude": 1.2926312574
    },
    {
      "Longitude": 103.85226,
      "Latitude": 1.29341
    },
    {
      "Longitude": 103.863,
      "Latitude": 1.29353
    },
    {
      "Longitude": 103.8545402884,
      "Latitude": 1.2936680024
    },
    {
      "Longitude": 103.82036,
      "Latitude": 1.29368
    },
    {
      "Longitude": 103.85506,
      "Latitude": 1.29369
    },
    {
      "Longitude": 103.85235,
      "Latitude": 1.29382
    },
    {
      "Longitude": 103.8440431282,
      "Latitude": 1.2938892282
    },
    {
      "Longitude": 103.8525,
      "Latitude": 1.29427
    },
    {
      "Longitude": 103.85879,
      "Latitude": 1.29447
    },
    {
      "Longitude": 103.8505622372,
      "Latitude": 1.2945234088
    },
    {
      "Longitude": 103.85269,
      "Latitude": 1.29455
    },
    {
      "Longitude": 103.8593213,
      "Latitude": 1.2948174
    },
    {
      "Longitude": 103.86928,
      "Latitude": 1.29488
    },
    {
      "Longitude": 103.8587439805,
      "Latitude": 1.2953523349
    },
    {
      "Longitude": 103.7651567,
      "Latitude": 1.2954418
    },
    {
      "Longitude": 103.87993,
      "Latitude": 1.29564
    },
    {
      "Longitude": 103.88151,
      "Latitude": 1.29575
    },
    {
      "Longitude": 103.8550036401,
      "Latitude": 1.2957830546
    },
    {
      "Longitude": 103.79312,
      "Latitude": 1.29614
    },
    {
      "Longitude": 103.8522208482,
      "Latitude": 1.2962188021
    },
    {
      "Longitude": 103.89531,
      "Latitude": 1.29634
    },
    {
      "Longitude": 103.81266,
      "Latitude": 1.29672
    },
    {
      "Longitude": 103.8505598903,
      "Latitude": 1.2971003525
    },
    {
      "Longitude": 103.8775385544,
      "Latitude": 1.29752772
    },
    {
      "Longitude": 103.85224,
      "Latitude": 1.29799
    },
    {
      "Longitude": 103.85799,
      "Latitude": 1.29838
    },
    {
      "Longitude": 103.6676516756,
      "Latitude": 1.2984930675
    },
    {
      "Longitude": 103.80321,
      "Latitude": 1.2985
    },
    {
      "Longitude": 103.8978790864,
      "Latitude": 1.2988493744
    },
    {
      "Longitude": 103.85713,
      "Latitude": 1.29902
    },
    {
      "Longitude": 103.7633397,
      "Latitude": 1.2992808
    },
    {
      "Longitude": 103.85277,
      "Latitude": 1.29998
    },
    {
      "Longitude": 103.85274,
      "Latitude": 1.30006
    },
    {
      "Longitude": 103.83863,
      "Latitude": 1.3001
    },
    {
      "Longitude": 103.85567,
      "Latitude": 1.30018
    },
    {
      "Longitude": 103.85265,
      "Latitude": 1.30019
    },
    {
      "Longitude": 103.85904,
      "Latitude": 1.30031
    },
    {
      "Longitude": 103.8357531,
      "Latitude": 1.3003621
    },
    {
      "Longitude": 103.79999,
      "Latitude": 1.30073
    },
    {
      "Longitude": 103.8433397189,
      "Latitude": 1.3009711261
    },
    {
      "Longitude": 103.85547,
      "Latitude": 1.30098
    },
    {
      "Longitude": 103.8352086022,
      "Latitude": 1.3010840851
    },
    {
      "Longitude": 103.8353114,
      "Latitude": 1.3011727
    },
    {
      "Longitude": 103.91014,
      "Latitude": 1.30151
    },
    {
      "Longitude": 103.83822,
      "Latitude": 1.30156
    },
    {
      "Longitude": 103.83429,
      "Latitude": 1.30171
    },
    {
      "Longitude": 103.8346899301,
      "Latitude": 1.3019153554
    },
    {
      "Longitude": 103.7117233,
      "Latitude": 1.3022367
    },
    {
      "Longitude": 103.85308,
      "Latitude": 1.30228
    },
    {
      "Longitude": 103.90582,
      "Latitude": 1.30254
    },
    {
      "Longitude": 103.86395,
      "Latitude": 1.30264
    },
    {
      "Longitude": 103.90058,
      "Latitude": 1.30313
    },
    {
      "Longitude": 103.7654202059,
      "Latitude": 1.3032527614
    },
    {
      "Longitude": 103.83341,
      "Latitude": 1.30357
    },
    {
      "Longitude": 103.83656,
      "Latitude": 1.3036
    },
    {
      "Longitude": 103.85378,
      "Latitude": 1.30362
    },
    {
      "Longitude": 103.83652,
      "Latitude": 1.30375
    },
    {
      "Longitude": 103.91922,
      "Latitude": 1.30399
    },
    {
      "Longitude": 103.90796,
      "Latitude": 1.30404
    },
    {
      "Longitude": 103.8335553557,
      "Latitude": 1.3042378829
    },
    {
      "Longitude": 103.8330728,
      "Latitude": 1.3043524
    },
    {
      "Longitude": 103.8371491805,
      "Latitude": 1.3052980863
    },
    {
      "Longitude": 103.8313712,
      "Latitude": 1.3054265
    },
    {
      "Longitude": 103.83884,
      "Latitude": 1.30615
    },
    {
      "Longitude": 103.91226,
      "Latitude": 1.30615
    },
    {
      "Longitude": 103.7892074,
      "Latitude": 1.3071097
    },
    {
      "Longitude": 103.8338,
      "Latitude": 1.30726
    },
    {
      "Longitude": 103.86147,
      "Latitude": 1.3073
    },
    {
      "Longitude": 103.93484,
      "Latitude": 1.3075
    },
    {
      "Longitude": 103.83325,
      "Latitude": 1.30788
    },
    {
      "Longitude": 103.77653,
      "Latitude": 1.3081
    },
    {
      "Longitude": 103.82706,
      "Latitude": 1.30889
    },
    {
      "Longitude": 103.91228,
      "Latitude": 1.30916
    },
    {
      "Longitude": 103.84598203,
      "Latitude": 1.3096458207
    },
    {
      "Longitude": 103.76921,
      "Latitude": 1.30971
    },
    {
      "Longitude": 103.8269132003,
      "Latitude": 1.3097698404
    },
    {
      "Longitude": 103.85573,
      "Latitude": 1.30978
    },
    {
      "Longitude": 103.8578,
      "Latitude": 1.30982
    },
    {
      "Longitude": 103.8260548,
      "Latitude": 1.3100551
    },
    {
      "Longitude": 103.87582,
      "Latitude": 1.31045
    },
    {
      "Longitude": 103.8267356,
      "Latitude": 1.3106498
    },
    {
      "Longitude": 103.83994,
      "Latitude": 1.31081
    },
    {
      "Longitude": 103.84449,
      "Latitude": 1.31094
    },
    {
      "Longitude": 103.85649,
      "Latitude": 1.31117
    },
    {
      "Longitude": 103.85495,
      "Latitude": 1.31122
    },
    {
      "Longitude": 103.6334307119,
      "Latitude": 1.3115999691
    },
    {
      "Longitude": 103.87654,
      "Latitude": 1.31201
    },
    {
      "Longitude": 103.77755,
      "Latitude": 1.3122
    },
    {
      "Longitude": 103.85968,
      "Latitude": 1.31237
    },
    {
      "Longitude": 103.8393690437,
      "Latitude": 1.3126956994
    },
    {
      "Longitude": 103.8302562386,
      "Latitude": 1.3128043003
    },
    {
      "Longitude": 103.8816,
      "Latitude": 1.31294
    },
    {
      "Longitude": 103.7659,
      "Latitude": 1.31344
    },
    {
      "Longitude": 103.98837,
      "Latitude": 1.31461
    },
    {
      "Longitude": 103.8963230699,
      "Latitude": 1.314959559
    },
    {
      "Longitude": 103.8933293894,
      "Latitude": 1.3153376509
    },
    {
      "Longitude": 103.84178,
      "Latitude": 1.31598
    },
    {
      "Longitude": 103.8992,
      "Latitude": 1.31651
    },
    {
      "Longitude": 103.76175,
      "Latitude": 1.31665
    },
    {
      "Longitude": 103.7717733532,
      "Latitude": 1.3167766116
    },
    {
      "Longitude": 103.76612,
      "Latitude": 1.31748
    },
    {
      "Longitude": 103.76865,
      "Latitude": 1.31785
    },
    {
      "Longitude": 103.8546690345,
      "Latitude": 1.3186265112
    },
    {
      "Longitude": 103.86034,
      "Latitude": 1.31868
    },
    {
      "Longitude": 103.88544,
      "Latitude": 1.31872
    },
    {
      "Longitude": 103.8256737,
      "Latitude": 1.3188842
    },
    {
      "Longitude": 103.93263,
      "Latitude": 1.31896
    },
    {
      "Longitude": 103.795063,
      "Latitude": 1.3192105
    },
    {
      "Longitude": 103.85145,
      "Latitude": 1.31927
    },
    {
      "Longitude": 103.84349,
      "Latitude": 1.31946
    },
    {
      "Longitude": 103.85367,
      "Latitude": 1.31951
    },
    {
      "Longitude": 103.8433333486,
      "Latitude": 1.3196853678
    },
    {
      "Longitude": 103.98057,
      "Latitude": 1.32031
    },
    {
      "Longitude": 103.85294,
      "Latitude": 1.32044
    },
    {
      "Longitude": 103.8255372,
      "Latitude": 1.3210418
    },
    {
      "Longitude": 103.88208,
      "Latitude": 1.32114
    },
    {
      "Longitude": 103.7476,
      "Latitude": 1.32154
    },
    {
      "Longitude": 103.84668,
      "Latitude": 1.32175
    },
    {
      "Longitude": 103.8462354988,
      "Latitude": 1.3218221852
    },
    {
      "Longitude": 103.85332,
      "Latitude": 1.32265
    },
    {
      "Longitude": 103.88999,
      "Latitude": 1.32279
    },
    {
      "Longitude": 103.81938,
      "Latitude": 1.32293
    },
    {
      "Longitude": 103.7691,
      "Latitude": 1.32338
    },
    {
      "Longitude": 103.85547,
      "Latitude": 1.32354
    },
    {
      "Longitude": 103.861,
      "Latitude": 1.32355
    },
    {
      "Longitude": 103.67853,
      "Latitude": 1.3242
    },
    {
      "Longitude": 103.859,
      "Latitude": 1.32458
    },
    {
      "Longitude": 103.69024,
      "Latitude": 1.32471
    },
    {
      "Longitude": 103.8659510761,
      "Latitude": 1.3251184111
    },
    {
      "Longitude": 103.90567,
      "Latitude": 1.32556
    },
    {
      "Longitude": 103.9057,
      "Latitude": 1.32557
    },
    {
      "Longitude": 103.83329,
      "Latitude": 1.32588
    },
    {
      "Longitude": 103.88803,
      "Latitude": 1.32603
    },
    {
      "Longitude": 103.7397,
      "Latitude": 1.32655
    },
    {
      "Longitude": 103.80694,
      "Latitude": 1.32692
    },
    {
      "Longitude": 103.72522,
      "Latitude": 1.32727
    },
    {
      "Longitude": 103.67531,
      "Latitude": 1.32752
    },
    {
      "Longitude": 103.7088,
      "Latitude": 1.32817
    },
    {
      "Longitude": 103.814249821,
      "Latitude": 1.3287256852
    },
    {
      "Longitude": 103.92826,
      "Latitude": 1.32891
    },
    {
      "Longitude": 103.93496,
      "Latitude": 1.32894
    },
    {
      "Longitude": 103.92481,
      "Latitude": 1.33099
    },
    {
      "Longitude": 103.72185,
      "Latitude": 1.33126
    },
    {
      "Longitude": 103.97639,
      "Latitude": 1.33158
    },
    {
      "Longitude": 103.8169,
      "Latitude": 1.33172
    },
    {
      "Longitude": 103.8445,
      "Latitude": 1.33176
    },
    {
      "Longitude": 103.91802,
      "Latitude": 1.33182
    },
    {
      "Longitude": 103.7423,
      "Latitude": 1.33191
    },
    {
      "Longitude": 103.74321,
      "Latitude": 1.33211
    },
    {
      "Longitude": 103.91484,
      "Latitude": 1.33256
    },
    {
      "Longitude": 103.9205475,
      "Latitude": 1.3329698
    },
    {
      "Longitude": 103.8890659,
      "Latitude": 1.333637
    },
    {
      "Longitude": 103.9339684,
      "Latitude": 1.3336694
    },
    {
      "Longitude": 103.76486,
      "Latitude": 1.33368
    },
    {
      "Longitude": 103.8468785584,
      "Latitude": 1.3338567068
    },
    {
      "Longitude": 103.888991,
      "Latitude": 1.3340346
    },
    {
      "Longitude": 103.72259,
      "Latitude": 1.33463
    },
    {
      "Longitude": 103.95154,
      "Latitude": 1.33479
    },
    {
      "Longitude": 103.9257226,
      "Latitude": 1.3351332
    },
    {
      "Longitude": 103.75968,
      "Latitude": 1.3359
    },
    {
      "Longitude": 103.9335829,
      "Latitude": 1.3359733
    },
    {
      "Longitude": 103.95844,
      "Latitude": 1.3363441
    },
    {
      "Longitude": 103.9589488,
      "Latitude": 1.3365428
    },
    {
      "Longitude": 103.92103,
      "Latitude": 1.33697
    },
    {
      "Longitude": 103.7408652529,
      "Latitude": 1.3371669943
    },
    {
      "Longitude": 103.7176923081,
      "Latitude": 1.337451231
    },
    {
      "Longitude": 103.72477,
      "Latitude": 1.33748
    },
    {
      "Longitude": 103.77753,
      "Latitude": 1.33767
    },
    {
      "Longitude": 103.9327313751,
      "Latitude": 1.3379734489
    },
    {
      "Longitude": 103.7171223387,
      "Latitude": 1.3381326616
    },
    {
      "Longitude": 103.87076,
      "Latitude": 1.33834
    },
    {
      "Longitude": 103.707251139,
      "Latitude": 1.3390383305
    },
    {
      "Longitude": 103.88313,
      "Latitude": 1.33924
    },
    {
      "Longitude": 103.9831548929,
      "Latitude": 1.3392803337
    },
    {
      "Longitude": 103.74161,
      "Latitude": 1.33959
    },
    {
      "Longitude": 103.98131,
      "Latitude": 1.33976
    },
    {
      "Longitude": 103.9817539,
      "Latitude": 1.3401889
    },
    {
      "Longitude": 103.7599444762,
      "Latitude": 1.3404109109
    },
    {
      "Longitude": 103.9831,
      "Latitude": 1.34079
    },
    {
      "Longitude": 103.9830576628,
      "Latitude": 1.3408523487
    },
    {
      "Longitude": 103.98304,
      "Latitude": 1.34095
    },
    {
      "Longitude": 103.84609,
      "Latitude": 1.34101
    },
    {
      "Longitude": 103.7430576235,
      "Latitude": 1.3410685426
    },
    {
      "Longitude": 103.9825909585,
      "Latitude": 1.3416417077
    },
    {
      "Longitude": 103.77578,
      "Latitude": 1.34177
    },
    {
      "Longitude": 103.7338459119,
      "Latitude": 1.3419336531
    },
    {
      "Longitude": 103.85842,
      "Latitude": 1.34204
    },
    {
      "Longitude": 103.7758,
      "Latitude": 1.34224
    },
    {
      "Longitude": 103.77567,
      "Latitude": 1.34233
    },
    {
      "Longitude": 103.7756,
      "Latitude": 1.34237
    },
    {
      "Longitude": 103.98333,
      "Latitude": 1.34273
    },
    {
      "Longitude": 103.9831579,
      "Latitude": 1.3429676
    },
    {
      "Longitude": 103.71642,
      "Latitude": 1.34303
    },
    {
      "Longitude": 103.7161024287,
      "Latitude": 1.3432542784
    },
    {
      "Longitude": 103.71037,
      "Latitude": 1.34413
    },
    {
      "Longitude": 103.72215,
      "Latitude": 1.34487
    },
    {
      "Longitude": 103.7232371047,
      "Latitude": 1.3451155544
    },
    {
      "Longitude": 103.7490570545,
      "Latitude": 1.3451899652
    },
    {
      "Longitude": 103.85112,
      "Latitude": 1.34527
    },
    {
      "Longitude": 103.73022,
      "Latitude": 1.34579
    },
    {
      "Longitude": 103.73278,
      "Latitude": 1.34616
    },
    {
      "Longitude": 103.94259,
      "Latitude": 1.34624
    },
    {
      "Longitude": 103.7431525066,
      "Latitude": 1.3463071323
    },
    {
      "Longitude": 103.73769,
      "Latitude": 1.34631
    },
    {
      "Longitude": 103.98409,
      "Latitude": 1.34721
    },
    {
      "Longitude": 103.85483,
      "Latitude": 1.34809
    },
    {
      "Longitude": 103.73137,
      "Latitude": 1.34837
    },
    {
      "Longitude": 103.87288,
      "Latitude": 1.34842
    },
    {
      "Longitude": 103.73134,
      "Latitude": 1.34851
    },
    {
      "Longitude": 103.7143198,
      "Latitude": 1.34892
    },
    {
      "Longitude": 103.83967,
      "Latitude": 1.34913
    },
    {
      "Longitude": 103.95093,
      "Latitude": 1.34955
    },
    {
      "Longitude": 103.73963,
      "Latitude": 1.34999
    },
    {
      "Longitude": 103.84933,
      "Latitude": 1.35005
    },
    {
      "Longitude": 103.7131454,
      "Latitude": 1.3500599
    },
    {
      "Longitude": 103.94171,
      "Latitude": 1.35015
    },
    {
      "Longitude": 103.87374,
      "Latitude": 1.35021
    },
    {
      "Longitude": 103.87322,
      "Latitude": 1.35047
    },
    {
      "Longitude": 103.7241795659,
      "Latitude": 1.3505907746
    },
    {
      "Longitude": 103.70283,
      "Latitude": 1.35072
    },
    {
      "Longitude": 103.71794,
      "Latitude": 1.35135
    },
    {
      "Longitude": 103.71208,
      "Latitude": 1.35144
    },
    {
      "Longitude": 103.98468,
      "Latitude": 1.3516
    },
    {
      "Longitude": 103.9599185809,
      "Latitude": 1.3516841412
    },
    {
      "Longitude": 103.848,
      "Latitude": 1.35169
    },
    {
      "Longitude": 103.98504,
      "Latitude": 1.35186
    },
    {
      "Longitude": 103.98514,
      "Latitude": 1.35192
    },
    {
      "Longitude": 103.984760195,
      "Latitude": 1.3520602163
    },
    {
      "Longitude": 103.9433,
      "Latitude": 1.35216
    },
    {
      "Longitude": 103.98516,
      "Latitude": 1.35221
    },
    {
      "Longitude": 103.87258,
      "Latitude": 1.35234
    },
    {
      "Longitude": 103.8874754682,
      "Latitude": 1.352353166
    },
    {
      "Longitude": 103.9857,
      "Latitude": 1.35243
    },
    {
      "Longitude": 103.98587,
      "Latitude": 1.35289
    },
    {
      "Longitude": 103.986,
      "Latitude": 1.35319
    },
    {
      "Longitude": 103.98603,
      "Latitude": 1.35322
    },
    {
      "Longitude": 103.98606,
      "Latitude": 1.35334
    },
    {
      "Longitude": 103.98615,
      "Latitude": 1.35354
    },
    {
      "Longitude": 103.95623,
      "Latitude": 1.35376
    },
    {
      "Longitude": 103.7189,
      "Latitude": 1.35385
    },
    {
      "Longitude": 103.98626,
      "Latitude": 1.35388
    },
    {
      "Longitude": 103.89144,
      "Latitude": 1.35412
    },
    {
      "Longitude": 103.9865703,
      "Latitude": 1.354171
    },
    {
      "Longitude": 103.9867021,
      "Latitude": 1.3543527
    },
    {
      "Longitude": 103.987874575,
      "Latitude": 1.3544979994
    },
    {
      "Longitude": 103.87268,
      "Latitude": 1.35456
    },
    {
      "Longitude": 103.98742,
      "Latitude": 1.3547
    },
    {
      "Longitude": 103.98729,
      "Latitude": 1.35492
    },
    {
      "Longitude": 103.7313263118,
      "Latitude": 1.3552122731
    },
    {
      "Longitude": 103.93668,
      "Latitude": 1.35591
    },
    {
      "Longitude": 103.98871,
      "Latitude": 1.35591
    },
    {
      "Longitude": 103.8553781435,
      "Latitude": 1.3562741306
    },
    {
      "Longitude": 103.95689,
      "Latitude": 1.35639
    },
    {
      "Longitude": 103.9885887131,
      "Latitude": 1.3567068507
    },
    {
      "Longitude": 103.98983,
      "Latitude": 1.35697
    },
    {
      "Longitude": 103.9889400825,
      "Latitude": 1.3570051628
    },
    {
      "Longitude": 103.9891181141,
      "Latitude": 1.3573195636
    },
    {
      "Longitude": 103.99026,
      "Latitude": 1.3574
    },
    {
      "Longitude": 103.9898192,
      "Latitude": 1.3575054
    },
    {
      "Longitude": 103.9893950522,
      "Latitude": 1.3575350857
    },
    {
      "Longitude": 103.9898358,
      "Latitude": 1.3575367
    },
    {
      "Longitude": 103.98993,
      "Latitude": 1.35754
    },
    {
      "Longitude": 103.98988,
      "Latitude": 1.35757
    },
    {
      "Longitude": 103.98989,
      "Latitude": 1.3576
    },
    {
      "Longitude": 103.8682074845,
      "Latitude": 1.3576195515
    },
    {
      "Longitude": 103.94775,
      "Latitude": 1.35767
    },
    {
      "Longitude": 103.9896696433,
      "Latitude": 1.3578028961
    },
    {
      "Longitude": 103.9880935103,
      "Latitude": 1.3578545141
    },
    {
      "Longitude": 103.98857,
      "Latitude": 1.35802
    },
    {
      "Longitude": 103.74181,
      "Latitude": 1.35808
    },
    {
      "Longitude": 103.99008,
      "Latitude": 1.35849
    },
    {
      "Longitude": 103.99013,
      "Latitude": 1.35861
    },
    {
      "Longitude": 103.9902,
      "Latitude": 1.35869
    },
    {
      "Longitude": 103.83123,
      "Latitude": 1.35891
    },
    {
      "Longitude": 103.8914914057,
      "Latitude": 1.3594248412
    },
    {
      "Longitude": 103.98878,
      "Latitude": 1.35949
    },
    {
      "Longitude": 103.9881307,
      "Latitude": 1.3597148
    },
    {
      "Longitude": 103.88289,
      "Latitude": 1.36002
    },
    {
      "Longitude": 103.9880659,
      "Latitude": 1.3600969
    },
    {
      "Longitude": 103.947721906,
      "Latitude": 1.3603519537
    },
    {
      "Longitude": 103.98857,
      "Latitude": 1.36062
    },
    {
      "Longitude": 103.88842,
      "Latitude": 1.36068
    },
    {
      "Longitude": 103.9884499088,
      "Latitude": 1.3607467977
    },
    {
      "Longitude": 103.84172,
      "Latitude": 1.3609
    },
    {
      "Longitude": 103.98877,
      "Latitude": 1.36098
    },
    {
      "Longitude": 103.73116,
      "Latitude": 1.36101
    },
    {
      "Longitude": 103.9887,
      "Latitude": 1.36103
    },
    {
      "Longitude": 103.98915,
      "Latitude": 1.36109
    },
    {
      "Longitude": 103.9888,
      "Latitude": 1.36121
    },
    {
      "Longitude": 103.9892854,
      "Latitude": 1.3612709
    },
    {
      "Longitude": 103.9892766,
      "Latitude": 1.3612713
    },
    {
      "Longitude": 103.9890273,
      "Latitude": 1.3612813
    },
    {
      "Longitude": 103.9889964,
      "Latitude": 1.3612896
    },
    {
      "Longitude": 103.9890056,
      "Latitude": 1.3613162
    },
    {
      "Longitude": 103.9891024,
      "Latitude": 1.3615142
    },
    {
      "Longitude": 103.98915,
      "Latitude": 1.36164
    },
    {
      "Longitude": 103.96285,
      "Latitude": 1.36289
    },
    {
      "Longitude": 103.84247,
      "Latitude": 1.36423
    },
    {
      "Longitude": 103.77671,
      "Latitude": 1.36503
    },
    {
      "Longitude": 103.8711,
      "Latitude": 1.3658
    },
    {
      "Longitude": 103.85114,
      "Latitude": 1.36622
    },
    {
      "Longitude": 103.89249,
      "Latitude": 1.3668
    },
    {
      "Longitude": 103.77554,
      "Latitude": 1.36738
    },
    {
      "Longitude": 103.8759891,
      "Latitude": 1.3679159
    },
    {
      "Longitude": 103.7488562241,
      "Latitude": 1.3687170672
    },
    {
      "Longitude": 103.8481809,
      "Latitude": 1.3690135
    },
    {
      "Longitude": 103.848164,
      "Latitude": 1.3690241
    },
    {
      "Longitude": 103.86189,
      "Latitude": 1.36948
    },
    {
      "Longitude": 103.8765447,
      "Latitude": 1.3700374
    },
    {
      "Longitude": 103.83938,
      "Latitude": 1.37037
    },
    {
      "Longitude": 103.8555709,
      "Latitude": 1.3706689
    },
    {
      "Longitude": 103.88588,
      "Latitude": 1.37073
    },
    {
      "Longitude": 103.96685,
      "Latitude": 1.37117
    },
    {
      "Longitude": 103.871839866,
      "Latitude": 1.3715439776
    },
    {
      "Longitude": 103.86615,
      "Latitude": 1.37166
    },
    {
      "Longitude": 103.86661,
      "Latitude": 1.37181
    },
    {
      "Longitude": 103.8736191764,
      "Latitude": 1.3727512959
    },
    {
      "Longitude": 103.83726,
      "Latitude": 1.37329
    },
    {
      "Longitude": 103.9481,
      "Latitude": 1.37386
    },
    {
      "Longitude": 103.935,
      "Latitude": 1.37441
    },
    {
      "Longitude": 103.7714437768,
      "Latitude": 1.3745914328
    },
    {
      "Longitude": 103.84024,
      "Latitude": 1.37486
    },
    {
      "Longitude": 103.94075,
      "Latitude": 1.37513
    },
    {
      "Longitude": 103.94902,
      "Latitude": 1.37542
    },
    {
      "Longitude": 103.8363773748,
      "Latitude": 1.3757645613
    },
    {
      "Longitude": 103.94458,
      "Latitude": 1.37588
    },
    {
      "Longitude": 103.94735,
      "Latitude": 1.37598
    },
    {
      "Longitude": 103.88535,
      "Latitude": 1.3764
    },
    {
      "Longitude": 103.7454404309,
      "Latitude": 1.3766366981
    },
    {
      "Longitude": 103.8982,
      "Latitude": 1.37695
    },
    {
      "Longitude": 103.92507,
      "Latitude": 1.37732
    },
    {
      "Longitude": 103.76623,
      "Latitude": 1.37772
    },
    {
      "Longitude": 103.75616,
      "Latitude": 1.37784
    },
    {
      "Longitude": 103.89816,
      "Latitude": 1.37966
    },
    {
      "Longitude": 103.74497,
      "Latitude": 1.37985
    },
    {
      "Longitude": 103.73846,
      "Latitude": 1.3801
    },
    {
      "Longitude": 103.75452,
      "Latitude": 1.38036
    },
    {
      "Longitude": 103.73509,
      "Latitude": 1.38099
    },
    {
      "Longitude": 103.76288,
      "Latitude": 1.38187
    },
    {
      "Longitude": 103.74666,
      "Latitude": 1.38222
    },
    {
      "Longitude": 103.76633,
      "Latitude": 1.38289
    },
    {
      "Longitude": 103.7582509965,
      "Latitude": 1.3867021129
    },
    {
      "Longitude": 103.89801,
      "Latitude": 1.38742
    },
    {
      "Longitude": 103.84865,
      "Latitude": 1.38779
    },
    {
      "Longitude": 103.98337,
      "Latitude": 1.38793
    },
    {
      "Longitude": 103.8764529303,
      "Latitude": 1.3880602535
    },
    {
      "Longitude": 103.8689477742,
      "Latitude": 1.3885962026
    },
    {
      "Longitude": 103.86477,
      "Latitude": 1.38928
    },
    {
      "Longitude": 103.871,
      "Latitude": 1.38944
    },
    {
      "Longitude": 103.83894,
      "Latitude": 1.39135
    },
    {
      "Longitude": 103.7463460118,
      "Latitude": 1.3914556016
    },
    {
      "Longitude": 103.90538,
      "Latitude": 1.39239
    },
    {
      "Longitude": 103.89413,
      "Latitude": 1.39305
    },
    {
      "Longitude": 103.91538,
      "Latitude": 1.39322
    },
    {
      "Longitude": 103.89315,
      "Latitude": 1.39404
    },
    {
      "Longitude": 103.91234,
      "Latitude": 1.39423
    },
    {
      "Longitude": 103.88766,
      "Latitude": 1.3945
    },
    {
      "Longitude": 103.900581412,
      "Latitude": 1.3945244826
    },
    {
      "Longitude": 103.7519545108,
      "Latitude": 1.3946776584
    },
    {
      "Longitude": 103.91134,
      "Latitude": 1.39478
    },
    {
      "Longitude": 103.81667,
      "Latitude": 1.39524
    },
    {
      "Longitude": 103.88781,
      "Latitude": 1.3955
    },
    {
      "Longitude": 103.84019,
      "Latitude": 1.39579
    },
    {
      "Longitude": 103.75013,
      "Latitude": 1.39654
    },
    {
      "Longitude": 103.74798,
      "Latitude": 1.3971
    },
    {
      "Longitude": 103.747981824,
      "Latitude": 1.3984302949
    },
    {
      "Longitude": 103.748469986,
      "Latitude": 1.3999100977
    },
    {
      "Longitude": 103.89602,
      "Latitude": 1.40017
    },
    {
      "Longitude": 103.7433731183,
      "Latitude": 1.4003813551
    },
    {
      "Longitude": 103.9130903,
      "Latitude": 1.400592
    },
    {
      "Longitude": 103.744857721,
      "Latitude": 1.4011757221
    },
    {
      "Longitude": 103.9133557,
      "Latitude": 1.4012663
    },
    {
      "Longitude": 103.87747,
      "Latitude": 1.40142
    },
    {
      "Longitude": 103.86118,
      "Latitude": 1.40283
    },
    {
      "Longitude": 103.7864,
      "Latitude": 1.40484
    },
    {
      "Longitude": 103.8668278232,
      "Latitude": 1.4048951658
    },
    {
      "Longitude": 103.91224,
      "Latitude": 1.40557
    },
    {
      "Longitude": 103.80725,
      "Latitude": 1.40748
    },
    {
      "Longitude": 103.78185,
      "Latitude": 1.40761
    },
    {
      "Longitude": 103.83452,
      "Latitude": 1.4117
    },
    {
      "Longitude": 103.7861154601,
      "Latitude": 1.4118225595
    },
    {
      "Longitude": 103.84473,
      "Latitude": 1.41256
    },
    {
      "Longitude": 103.83111,
      "Latitude": 1.41275
    },
    {
      "Longitude": 103.83511,
      "Latitude": 1.41444
    },
    {
      "Longitude": 103.80072,
      "Latitude": 1.41596
    },
    {
      "Longitude": 103.80297,
      "Latitude": 1.41708
    },
    {
      "Longitude": 103.84105,
      "Latitude": 1.41928
    },
    {
      "Longitude": 103.84888,
      "Latitude": 1.4221
    },
    {
      "Longitude": 103.8643529,
      "Latitude": 1.4221902
    },
    {
      "Longitude": 103.8626549,
      "Latitude": 1.4226987
    },
    {
      "Longitude": 103.83699,
      "Latitude": 1.42293
    },
    {
      "Longitude": 103.83816,
      "Latitude": 1.42321
    },
    {
      "Longitude": 103.83861,
      "Latitude": 1.42356
    },
    {
      "Longitude": 103.7590958923,
      "Latitude": 1.4240979523
    },
    {
      "Longitude": 103.77539,
      "Latitude": 1.42474
    },
    {
      "Longitude": 103.7944961,
      "Latitude": 1.4252717
    },
    {
      "Longitude": 103.8497,
      "Latitude": 1.42561
    },
    {
      "Longitude": 103.84965,
      "Latitude": 1.42565
    },
    {
      "Longitude": 103.8365854,
      "Latitude": 1.4272301
    },
    {
      "Longitude": 103.83119,
      "Latitude": 1.42749
    },
    {
      "Longitude": 103.83525,
      "Latitude": 1.42891
    },
    {
      "Longitude": 103.76171,
      "Latitude": 1.42969
    },
    {
      "Longitude": 103.8331060857,
      "Latitude": 1.4304920305
    },
    {
      "Longitude": 103.8481871411,
      "Latitude": 1.4315196665
    },
    {
      "Longitude": 103.77299,
      "Latitude": 1.43225
    },
    {
      "Longitude": 103.84122,
      "Latitude": 1.43333
    },
    {
      "Longitude": 103.8289,
      "Latitude": 1.43461
    },
    {
      "Longitude": 103.79633,
      "Latitude": 1.43695
    },
    {
      "Longitude": 103.84103,
      "Latitude": 1.4372
    },
    {
      "Longitude": 103.7966199964,
      "Latitude": 1.4372698613
    },
    {
      "Longitude": 103.83764,
      "Latitude": 1.43755
    },
    {
      "Longitude": 103.78899,
      "Latitude": 1.4378
    },
    {
      "Longitude": 103.83931,
      "Latitude": 1.44081
    },
    {
      "Longitude": 103.81959,
      "Latitude": 1.44449
    },
    {
      "Longitude": 103.81773,
      "Latitude": 1.44484
    },
    {
      "Longitude": 103.81709,
      "Latitude": 1.44686
    },
    {
      "Longitude": 103.82448,
      "Latitude": 1.44948
    }
  ],
  "last_updated": "2025-12-28T10:29:52+00:00"
}
